{
  "ComponentIndexes": {
    "About": 23,
    "Component1": 24,
    "Footer": 25,
    "HomeImage": 26,
    "NavBar": 27,
    "UpcomingGuild": 28
  },
  "ControlUniqueGuids": {},
  "ControlUniqueIds": {
    "About": 34,
    "ActivityDetails": 44,
    "AddActivity": 75,
    "AddPicture1": 517,
    "AddPicture10": 562,
    "AddPicture2": 355,
    "AddPicture3": 416,
    "AddPicture5": 523,
    "AddPicture5_1": 496,
    "AddPicture6": 568,
    "AddPicture7": 529,
    "AddPicture8": 550,
    "AddPicture9": 556,
    "Admin": 112,
    "allBlogs": 191,
    "AllBlogs": 229,
    "App": 1,
    "Attachments_DataCard1": 570,
    "Attachments_DataCard2": 440,
    "Attachments_DataCard2_1": 70,
    "Attachments_DataCard2_2": 100,
    "Attachments_DataCard4": 699,
    "Body1_1": 136,
    "Body2": 337,
    "btnNext": 610,
    "btnPrevious": 609,
    "Button1": 661,
    "Button1_1": 753,
    "Button1_2": 643,
    "Button1_3": 665,
    "Button1_4": 657,
    "Button1_5": 647,
    "Button10": 404,
    "Button11": 214,
    "Button12": 15,
    "Button13": 278,
    "Button14": 446,
    "Button15": 241,
    "Button16": 18,
    "Button16_1": 17,
    "Button17": 641,
    "Button17_1": 322,
    "Button17_3": 158,
    "Button17_4": 209,
    "Button18": 648,
    "Button18_1": 656,
    "Button18_12": 162,
    "Button18_13": 161,
    "Button18_14": 160,
    "Button18_15": 159,
    "Button18_16": 226,
    "Button18_17": 218,
    "Button18_18": 217,
    "Button18_19": 212,
    "Button18_2": 658,
    "Button18_3": 660,
    "Button18_4": 326,
    "Button18_5": 325,
    "Button18_6": 324,
    "Button18_7": 323,
    "Button2": 223,
    "Button2_3": 7,
    "Button2_4": 463,
    "Button2_5": 5,
    "Button2_6": 6,
    "Button20_1": 580,
    "Button20_10": 291,
    "Button20_11": 292,
    "Button20_12": 290,
    "Button20_3": 116,
    "Button20_5": 579,
    "Button20_6": 115,
    "Button20_7": 194,
    "Button20_8": 195,
    "Button3": 40,
    "Button3_1": 134,
    "Button4": 704,
    "Button4_1": 133,
    "Button5": 646,
    "Button5_1": 459,
    "Button5_2": 709,
    "Button5_3": 575,
    "Button5_4": 120,
    "Button5_5": 210,
    "Button6": 359,
    "Button6_1": 68,
    "Button7": 393,
    "Button8": 394,
    "Button8_1": 135,
    "Button8_2": 105,
    "Button9": 330,
    "Canvas1": 585,
    "Canvas1_1": 242,
    "Canvas10": 710,
    "Canvas11": 79,
    "Canvas12": 169,
    "Canvas2": 235,
    "Canvas3": 232,
    "Canvas4": 343,
    "Canvas5": 294,
    "Canvas6": 121,
    "Canvas7": 366,
    "Canvas8": 401,
    "Canvas9": 48,
    "Category_Column1": 174,
    "Circle1_1": 286,
    "ColumnChart1": 299,
    "ColumnChart2": 308,
    "ColumnChart3": 728,
    "ColumnChart4": 188,
    "ColumnChart5": 187,
    "Communities_Column1_1": 747,
    "Community": 234,
    "CommunityRole_Column1_1": 748,
    "Component1": 3,
    "Component1_1": 578,
    "Component1_2": 193,
    "Component1_3": 289,
    "Component1_4": 114,
    "Component2_1": 587,
    "Component3_1": 590,
    "CompositeColumnChart1": 303,
    "CompositeColumnChart2": 312,
    "CompositeColumnChart2_1": 151,
    "CompositeColumnChart3": 189,
    "CompositeColumnChart4": 736,
    "CompositeColumnChart5": 190,
    "CompositeLineChart1": 302,
    "CompositeLineChart1_1": 150,
    "CompositeLineChart2": 734,
    "CompositePieChart3": 311,
    "CompositePieChart4": 735,
    "CompositePieChart5": 320,
    "Container1": 25,
    "Container2": 198,
    "Container3": 649,
    "Container5": 631,
    "content": 350,
    "content_1": 410,
    "Count_Column1": 175,
    "createBlog": 339,
    "Dashboard": 287,
    "DataCard1": 619,
    "DataCard10": 344,
    "DataCard11": 295,
    "DataCard12": 304,
    "DataCard13": 589,
    "DataCard14": 374,
    "DataCard15": 402,
    "DataCard16": 313,
    "DataCard17": 376,
    "DataCard18": 233,
    "DataCard19": 122,
    "DataCard2": 593,
    "DataCard2_1": 243,
    "DataCard20": 383,
    "DataCard21": 372,
    "DataCard22": 138,
    "DataCard23": 250,
    "DataCard24": 49,
    "DataCard25": 258,
    "DataCard26": 184,
    "DataCard27": 711,
    "DataCard28": 80,
    "DataCard29": 724,
    "DataCard3": 616,
    "DataCard30": 737,
    "DataCard31": 744,
    "DataCard32": 152,
    "DataCard33": 265,
    "DataCard34": 170,
    "DataCard35": 176,
    "DataCard4": 623,
    "DataCard5": 626,
    "DataCard6": 613,
    "DataCard7": 236,
    "DataCard8": 586,
    "DataCard9": 367,
    "DataCardKey1": 469,
    "DataCardKey10": 560,
    "DataCardKey11": 500,
    "DataCardKey12": 505,
    "DataCardKey13": 686,
    "DataCardKey14": 494,
    "DataCardKey15": 566,
    "DataCardKey17": 572,
    "DataCardKey18": 422,
    "DataCardKey18_1": 102,
    "DataCardKey19": 681,
    "DataCardKey2": 515,
    "DataCardKey20": 691,
    "DataCardKey22": 696,
    "DataCardKey23": 701,
    "DataCardKey24": 427,
    "DataCardKey25": 432,
    "DataCardKey26": 437,
    "DataCardKey27": 442,
    "DataCardKey29": 538,
    "DataCardKey3": 474,
    "DataCardKey31": 510,
    "DataCardKey32": 109,
    "DataCardKey33": 479,
    "DataCardKey34": 533,
    "DataCardKey35": 543,
    "DataCardKey4": 521,
    "DataCardKey4_1": 484,
    "DataCardKey43": 73,
    "DataCardKey5": 414,
    "DataCardKey6": 527,
    "DataCardKey6_1": 489,
    "DataCardKey7": 357,
    "DataCardKey8": 548,
    "DataCardKey9": 554,
    "DataCardValue1": 470,
    "DataCardValue11": 573,
    "DataCardValue12": 423,
    "DataCardValue13": 428,
    "DataCardValue14": 433,
    "DataCardValue15": 438,
    "DataCardValue16": 443,
    "DataCardValue17": 682,
    "DataCardValue17_1": 103,
    "DataCardValue18": 692,
    "DataCardValue2": 687,
    "DataCardValue20": 697,
    "DataCardValue21": 702,
    "DataCardValue23": 539,
    "DataCardValue25": 511,
    "DataCardValue26": 480,
    "DataCardValue27": 534,
    "DataCardValue28": 544,
    "DataCardValue3_1": 475,
    "DataCardValue31": 108,
    "DataCardValue4_1": 485,
    "DataCardValue42": 71,
    "DataCardValue5_1": 490,
    "DataCardValue8": 501,
    "DataCardValue8_1": 462,
    "DataCardValue9": 506,
    "DataTable1": 315,
    "DataTable1_1": 746,
    "DataTable2": 147,
    "DataTable3": 154,
    "DataTable3_1": 740,
    "DataTable4": 173,
    "Date_DataCard1": 435,
    "Date_DataCard2": 694,
    "DateofEvent_Column1_1": 742,
    "DatePicker1": 456,
    "DatePicker1_1": 90,
    "ddPageSize": 601,
    "Description_DataCard1": 425,
    "Description_DataCard3": 689,
    "Designation1_DataCard1": 487,
    "detailBlog": 360,
    "detailBlog2": 395,
    "Dropdown1": 216,
    "Dropdown1_1": 739,
    "Dropdown2": 348,
    "Dropdown2_1": 408,
    "Dropdown2_2": 84,
    "Dropdown3": 85,
    "Dropdown4": 91,
    "Dropdown5": 96,
    "Dropdown6": 126,
    "Dropdown7": 172,
    "DtopDownDash": 673,
    "DtopDownDash_1": 164,
    "DtopDownDash_2": 228,
    "editBlog": 397,
    "ErrorMessage1": 471,
    "ErrorMessage10": 563,
    "ErrorMessage11": 502,
    "ErrorMessage12": 507,
    "ErrorMessage13": 688,
    "ErrorMessage14": 497,
    "ErrorMessage15": 569,
    "ErrorMessage17": 574,
    "ErrorMessage18": 424,
    "ErrorMessage18_1": 104,
    "ErrorMessage19": 683,
    "ErrorMessage2": 518,
    "ErrorMessage20": 693,
    "ErrorMessage22": 698,
    "ErrorMessage23": 703,
    "ErrorMessage24": 429,
    "ErrorMessage25": 434,
    "ErrorMessage26": 439,
    "ErrorMessage27": 444,
    "ErrorMessage29": 540,
    "ErrorMessage3": 476,
    "ErrorMessage31": 512,
    "ErrorMessage32": 111,
    "ErrorMessage33": 481,
    "ErrorMessage34": 535,
    "ErrorMessage35": 545,
    "ErrorMessage4": 524,
    "ErrorMessage4_1": 486,
    "ErrorMessage43": 74,
    "ErrorMessage5": 417,
    "ErrorMessage6": 530,
    "ErrorMessage6_1": 491,
    "ErrorMessage7": 358,
    "ErrorMessage8": 551,
    "ErrorMessage9": 557,
    "EventDetails": 328,
    "EventEdit": 418,
    "EventForm": 676,
    "FAQs": 447,
    "Feedback": 450,
    "Feedback_Column1": 743,
    "FileUpload": 460,
    "Footer": 24,
    "Form1_1": 466,
    "Form2": 352,
    "Form2_1": 99,
    "Form3": 411,
    "Form3_1": 69,
    "Form3_2": 106,
    "Form4": 678,
    "Form5": 419,
    "FullDescription_DataCard1": 477,
    "Gallery1": 604,
    "Gallery1_1": 754,
    "Gallery11": 11,
    "Gallery12": 13,
    "Gallery18": 635,
    "Gallery18_1": 202,
    "Gallery2": 331,
    "Gallery2_1": 129,
    "Gallery3": 269,
    "Gallery4": 219,
    "Gallery5": 179,
    "Gallery7": 384,
    "Gallery9": 651,
    "galleryTemplate1": 595,
    "galleryTemplate1_1": 755,
    "galleryTemplate10": 652,
    "galleryTemplate11": 12,
    "galleryTemplate12": 14,
    "galleryTemplate18": 636,
    "galleryTemplate18_1": 203,
    "galleryTemplate2": 332,
    "galleryTemplate2_1": 280,
    "galleryTemplate2_2": 130,
    "galleryTemplate3": 605,
    "galleryTemplate3_1": 283,
    "galleryTemplate4": 220,
    "galleryTemplate5": 270,
    "galleryTemplate6": 180,
    "galleryTemplate7": 385,
    "galPaginated": 594,
    "Group1": 670,
    "Guild Form": 464,
    "Guild_DataCard1": 684,
    "GuildStats": 165,
    "Home": 576,
    "HomeDropDown": 672,
    "HomeImage": 42,
    "HtmlText2": 375,
    "HtmlText3": 396,
    "Icon1": 364,
    "Icon10": 381,
    "Icon10_1": 59,
    "Icon11": 599,
    "Icon12": 365,
    "Icon13": 377,
    "Icon14": 215,
    "Icon15": 342,
    "Icon16": 400,
    "Icon17": 329,
    "Icon18": 238,
    "Icon19": 445,
    "Icon2": 36,
    "Icon20": 650,
    "Icon21": 334,
    "Icon22": 16,
    "Icon23": 336,
    "Icon24": 675,
    "Icon25": 363,
    "Icon26": 600,
    "Icon27": 634,
    "Icon27_1": 201,
    "Icon29": 752,
    "Icon3": 583,
    "Icon3_1": 196,
    "Icon3_2": 293,
    "Icon3_3": 117,
    "Icon3_4": 582,
    "Icon3_5": 584,
    "Icon3_6": 118,
    "Icon3_7": 197,
    "Icon30": 275,
    "Icon31": 277,
    "Icon32": 168,
    "Icon33": 708,
    "Icon4": 452,
    "Icon4_2": 759,
    "Icon5": 632,
    "Icon5_1": 128,
    "Icon5_2": 78,
    "Icon5_3": 199,
    "Icon6": 603,
    "Icon7": 677,
    "Icon7_1": 47,
    "Icon8": 465,
    "Icon9": 664,
    "iconNextMonth1_1": 268,
    "iconPrevMonth1_1": 267,
    "Image_DataCard1": 564,
    "Image_DataCard2": 353,
    "Image_DataCard3": 412,
    "Image1": 4,
    "Image1_1": 10,
    "Image1_DataCard1": 492,
    "Image10": 621,
    "Image10_1": 261,
    "Image10_2": 259,
    "Image10_3": 260,
    "Image10_4": 622,
    "Image11": 33,
    "Image11_1": 29,
    "Image11_2": 30,
    "Image11_3": 31,
    "Image11_4": 50,
    "Image12": 627,
    "Image13": 628,
    "Image14": 666,
    "Image14_1": 667,
    "Image14_2": 668,
    "Image15": 221,
    "Image16": 380,
    "Image17": 368,
    "Image18": 415,
    "Image2": 43,
    "Image2_1": 756,
    "Image20": 495,
    "Image21": 567,
    "Image22": 630,
    "Image23": 373,
    "Image24": 386,
    "Image25": 21,
    "Image25_1": 22,
    "Image25_2": 23,
    "Image26": 581,
    "Image27": 522,
    "Image28": 528,
    "Image29": 549,
    "Image3": 596,
    "Image3_1": 244,
    "Image3_2": 253,
    "Image30": 555,
    "Image31": 561,
    "Image34": 181,
    "Image4": 516,
    "Image4_1": 254,
    "Image5": 38,
    "Image5_1": 252,
    "Image6": 629,
    "Image7": 28,
    "Image7_1": 715,
    "Image8": 354,
    "Image8_1": 124,
    "Image9": 246,
    "Label1": 617,
    "Label1_1": 761,
    "Label10": 87,
    "Label10_1": 125,
    "Label11": 345,
    "Label11_1": 349,
    "Label11_2": 405,
    "Label11_3": 409,
    "Label11_4": 454,
    "Label11_5": 89,
    "Label12": 240,
    "Label12_1": 457,
    "Label12_2": 88,
    "Label13": 239,
    "Label13_1": 139,
    "Label13_2": 98,
    "Label14": 448,
    "Label15": 369,
    "Label16": 371,
    "Label16_1": 51,
    "Label17": 370,
    "Label17_1": 52,
    "Label18": 378,
    "Label18_1": 53,
    "Label19": 249,
    "Label2": 41,
    "Label2_1": 123,
    "Label2_2": 760,
    "Label2_4": 717,
    "Label2_5": 713,
    "Label2_6": 720,
    "Label2_7": 722,
    "Label20": 20,
    "Label21": 379,
    "Label21_1": 54,
    "Label22": 391,
    "Label22_1": 55,
    "Label23": 347,
    "Label24": 392,
    "Label24_1": 56,
    "Label25": 351,
    "Label26": 407,
    "Label26_1": 57,
    "Label27": 247,
    "Label28": 403,
    "Label28_1": 58,
    "Label29": 245,
    "Label3": 26,
    "Label3_1": 461,
    "Label3_4": 714,
    "Label3_5": 718,
    "Label3_6": 723,
    "Label3_7": 719,
    "Label30": 248,
    "Label31": 153,
    "Label32": 60,
    "Label33": 64,
    "Label34": 61,
    "Label35": 62,
    "Label36": 65,
    "Label37": 67,
    "Label38": 66,
    "Label39": 63,
    "Label4": 27,
    "Label4_1": 738,
    "Label4_3": 745,
    "Label40": 272,
    "Label41": 273,
    "Label42": 178,
    "Label43": 602,
    "Label44": 276,
    "Label45": 274,
    "Label46": 171,
    "Label47": 607,
    "Label48": 177,
    "Label49": 612,
    "Label5": 32,
    "Label5_1": 251,
    "Label5_2": 712,
    "Label5_3": 93,
    "Label6": 588,
    "Label6_1": 721,
    "Label6_2": 94,
    "Label6_3": 95,
    "Label6_4": 255,
    "Label6_5": 256,
    "Label6_7": 257,
    "Label7": 449,
    "Label7_1": 81,
    "Label8": 663,
    "Label8_1": 453,
    "Label8_2": 82,
    "Label9": 83,
    "Label9_1": 264,
    "Label9_2": 263,
    "Label9_3": 262,
    "Label9_4": 127,
    "Label9_5": 451,
    "LblAppName1": 659,
    "LblAppName10": 77,
    "LblAppName2": 231,
    "LblAppName3": 341,
    "LblAppName4": 167,
    "LblAppName5": 751,
    "LblAppName6": 362,
    "LblAppName7": 399,
    "LblAppName8": 46,
    "LblAppName9": 707,
    "LblMonthSelected1_1": 266,
    "lblPagination": 611,
    "Legend1": 300,
    "Legend1_1": 145,
    "Legend10": 732,
    "Legend2": 301,
    "Legend4": 310,
    "Legend5_1": 144,
    "Legend6": 309,
    "Legend6_1": 733,
    "Legend8": 319,
    "Legend9": 731,
    "LineChart1": 298,
    "LineChart1_1": 143,
    "LineChart2": 730,
    "Link_DataCard1": 107,
    "Members_Column1": 156,
    "MicrosoftStream2": 620,
    "MonthDayGallery1_1": 282,
    "Name_Column1": 316,
    "Name_DataCard1": 430,
    "NavBar": 8,
    "NavBarGr": 671,
    "NavBarGr_1": 327,
    "NavBarGr_2": 163,
    "NavBarGr_3": 227,
    "NextArrow2": 758,
    "NextArrow20": 638,
    "NextArrow20_1": 205,
    "NextArrow6": 653,
    "No_Column1": 149,
    "PdfViewer1": 763,
    "PieChart3": 307,
    "PieChart4": 729,
    "PieChart5": 318,
    "Points_Column1": 317,
    "Polestar1_DataCard1": 482,
    "Profile": 705,
    "Rectangle1": 390,
    "Rectangle2": 644,
    "Rectangle2_1": 321,
    "Rectangle2_3": 157,
    "Rectangle2_4": 211,
    "Rectangle3": 642,
    "Rectangle4": 662,
    "Rectangle6": 645,
    "Rectangle6_1": 119,
    "Rectangle6_2": 208,
    "Rectangle7": 271,
    "Rectangle8": 9,
    "RectQuickActionBar1": 577,
    "RectQuickActionBar1_2": 237,
    "RectQuickActionBar10": 750,
    "RectQuickActionBar11": 45,
    "RectQuickActionBar12": 706,
    "RectQuickActionBar13": 76,
    "RectQuickActionBar2": 166,
    "RectQuickActionBar3": 230,
    "RectQuickActionBar4": 340,
    "RectQuickActionBar5": 288,
    "RectQuickActionBar6": 192,
    "RectQuickActionBar7": 361,
    "RectQuickActionBar8": 398,
    "RectQuickActionBar9": 113,
    "RichTextEditor1": 458,
    "Separator1": 225,
    "Separator2": 762,
    "Separator22": 640,
    "Separator22_1": 207,
    "Separator4": 608,
    "Separator5": 338,
    "Separator6_1": 137,
    "Separator7": 389,
    "Separator9": 655,
    "shareIt": 674,
    "Short Description_DataCard2": 472,
    "Star1_1": 716,
    "StarVisible1": 468,
    "StarVisible10": 559,
    "StarVisible11": 499,
    "StarVisible12": 504,
    "StarVisible13": 685,
    "StarVisible14": 493,
    "StarVisible15": 565,
    "StarVisible17": 571,
    "StarVisible18": 421,
    "StarVisible18_1": 101,
    "StarVisible19": 680,
    "StarVisible2": 514,
    "StarVisible20": 690,
    "StarVisible22": 695,
    "StarVisible23": 700,
    "StarVisible24": 426,
    "StarVisible25": 431,
    "StarVisible26": 436,
    "StarVisible27": 441,
    "StarVisible29": 537,
    "StarVisible3": 473,
    "StarVisible31": 509,
    "StarVisible32": 110,
    "StarVisible33": 478,
    "StarVisible34": 532,
    "StarVisible35": 542,
    "StarVisible4": 520,
    "StarVisible4_1": 483,
    "StarVisible43": 72,
    "StarVisible5": 413,
    "StarVisible6": 526,
    "StarVisible6_1": 488,
    "StarVisible7": 356,
    "StarVisible8": 547,
    "StarVisible9": 553,
    "Subcircle1_1": 285,
    "Subtitle1": 598,
    "Subtitle2": 224,
    "Subtitle20": 639,
    "Subtitle20_1": 206,
    "Subtitle6": 335,
    "Subtitle7": 183,
    "Subtitle7_1": 132,
    "Subtitle8": 388,
    "TextInput1": 35,
    "TextInput1_1": 97,
    "TextInput10": 615,
    "TextInput11": 625,
    "TextInput2": 39,
    "TextInput3": 37,
    "TextInput3_1": 455,
    "TextInput3_2": 86,
    "TextInput4": 624,
    "TextInput4_1": 92,
    "TextInput5": 382,
    "TextInput6": 213,
    "TextInput7": 618,
    "TextInput9": 591,
    "TextInput9_1": 592,
    "Timer1": 669,
    "title": 346,
    "title_1": 406,
    "Title_Column1": 155,
    "Title_Column2_1": 741,
    "Title_DataCard1": 467,
    "Title_DataCard2": 420,
    "Title_DataCard4": 679,
    "Title1": 597,
    "Title1_1": 142,
    "Title1_2": 146,
    "Title10": 314,
    "Title10_1": 726,
    "Title11": 333,
    "Title11_1": 725,
    "Title13": 387,
    "Title14": 182,
    "Title15": 606,
    "Title18": 654,
    "Title2": 296,
    "Title2_1": 281,
    "Title2_2": 757,
    "Title26": 637,
    "Title26_1": 204,
    "Title3": 297,
    "Title3_1": 284,
    "Title4": 222,
    "Title5": 306,
    "Title5_2": 141,
    "Title6": 185,
    "Title7": 727,
    "Title8": 305,
    "Title8_1": 131,
    "Title9": 186,
    "Top Communities_1": 140,
    "Torch Bearers1_DataCard1": 498,
    "Torch Bearers2_DataCard1": 503,
    "Torch Bearers3_DataCard1": 508,
    "TorchImage1_DataCard1": 513,
    "TorchImage2_DataCard1": 519,
    "TorchImage3_DataCard1": 525,
    "Trend Setters1_DataCard1": 531,
    "Trend Setters2_DataCard1": 536,
    "Trend Setters3_DataCard2": 541,
    "TrendImage1_DataCard1": 546,
    "TrendImage2_DataCard1": 552,
    "TrendImage3_DataCard1": 558,
    "UpcomingGuild": 19,
    "UpcomingGuild_1": 614,
    "UserName": 633,
    "UserName_1": 200,
    "UserName_Column1": 148,
    "WeekdayGallery1_1": 279,
    "WhitePapers": 749
  },
  "FunctionParamsInvariantScripts": {},
  "FunctionParamsInvariantScriptsOnInstances": {},
  "HeaderLastSavedDateTimeUTC": "12/29/2022 17:11:21",
  "IsLegacyComponentAllowGlobalScopeCase": false,
  "LocalConnectionIDReferences": {
    "55bd11ce-1540-4e1d-8336-43032c5b7e78": "\"/providers/microsoft.powerapps/apis/shared_office365/connections/e5e0684babb74ce59751a6b026425614\"",
    "59bc595d-2c49-4295-b900-697078d27880": "\"/providers/microsoft.powerapps/apis/shared_sharepointonline/connections/3b21a2f4b9454c77b1e0327cfd64b31b\"",
    "6cba9de9-2faa-4c8d-b993-358233bbe43e": "\"/providers/microsoft.powerapps/apis/shared_office365users/connections/d4c29c7a37634d3c9e15dd36612e80b6\"",
    "992a5415-928d-42ba-b621-3696bdd29ded": "\"/providers/microsoft.powerapps/apis/shared_logicflows/connections/771c2b3673f04eca893980534b0036ce\"",
    "9c8341d9-ee49-4114-9936-0c390c4fdcbe": "\"/providers/microsoft.powerapps/apis/shared_logicflows/connections/742e44f5b1fc4158a60afdacf5c33f7f\"",
    "e55f7f25-74ca-48aa-bbfc-87ca82df5358": "\"/providers/microsoft.powerapps/apis/shared_sharepointonline/connections/3b21a2f4b9454c77b1e0327cfd64b31b\""
  },
  "LocalDatabaseReferencesAsEmpty": false,
  "LocalResourceFileNames": {
    "237704527_10159698642244138_333429640887957773_n": "8ee15710-f80b-449f-bf97-5e337953ceaf.jpg",
    "Anand V": "0001.jpg",
    "baishali roy": "0002.jpg",
    "facebook-square": "0003.svg",
    "guild_product": "0004.jpg",
    "guild_supply": "0005.jpg",
    "guild_wealth": "0006.jpg",
    "Harshal Jawale": "0007.jpg",
    "Image": "0010.jpeg",
    "Image (1)": "0008.jpeg",
    "Image (2)": "0009.jpeg",
    "Image1_2": "0011.jpeg",
    "Image2_2": "0012.jpeg",
    "jayakanth abhimanyu": "0013.jpg",
    "linkedin": "0014.svg",
    "logo": "0015.jpg",
    "MicrosoftTeams-image (1)": "0016.png",
    "MicrosoftTeams-image (2)": "0017.png",
    "MicrosoftTeams-image (3)": "0018.png",
    "poojatest": "0019.PNG",
    "poojatest1": "0020.png",
    "priya": "0021.PNG",
    "priyatest": "0022.PNG",
    "priyatest1": "0023.png",
    "Quotes1": "0024.png",
    "Quotes2": "0025.png",
    "Rohan Kudav": "0026.jpg",
    "sanjeev korupolu": "0027.jpg",
    "soundarya cholkar": "0028.jpg",
    "square-facebook": "0029.svg",
    "square-twitter": "0030.svg",
    "testomonial": "0031.PNG",
    "youtube": "0032.svg"
  },
  "LocalResourceRootPaths": {
    "237704527_10159698642244138_333429640887957773_n": "https://docserverpwaprodcin.blob.core.windows.net/9b341c64-9324-42f1-b8c8-41b3bb579549-1/resource/Assets0Images08ee15710-f80b-449f-bf97-5e337953ceaf.jpg?sv=2017-04-17&sr=b&sig=TiZ%2BFoezTUUjdLcxbSNoNa5ki8gyWbMfje%2BBD%2Fxm38M%3D&spr=https&se=2022-12-30T16%3A52%3A12Z&sp=r",
    "Anand V": "https://docserverpwaprodcin.blob.core.windows.net/9b341c64-9324-42f1-b8c8-41b3bb579549-1/resource/Assets0Images00001.jpg?sv=2017-04-17&sr=b&sig=Ub58mV6hdZmz2g3i58mpOQ%2FqZPmIbZbAGScwyf5gBs4%3D&spr=https&se=2022-12-30T16%3A52%3A12Z&sp=r",
    "baishali roy": "https://docserverpwaprodcin.blob.core.windows.net/9b341c64-9324-42f1-b8c8-41b3bb579549-1/resource/Assets0Images00002.jpg?sv=2017-04-17&sr=b&sig=W8DBNI2l2XsHgFDeFrUJlKpvX4XuXKa1oulDxWIcRBc%3D&spr=https&se=2022-12-30T16%3A52%3A12Z&sp=r",
    "facebook-square": "https://docserverpwaprodcin.blob.core.windows.net/9b341c64-9324-42f1-b8c8-41b3bb579549-1/resource/Assets0Images00003.svg?sv=2017-04-17&sr=b&sig=MrSxCMpGspaPpOxvYWarjRDCMqhySqEFgeC%2FA8zvz4M%3D&spr=https&se=2022-12-30T16%3A52%3A12Z&sp=r",
    "guild_product": "https://docserverpwaprodcin.blob.core.windows.net/9b341c64-9324-42f1-b8c8-41b3bb579549-1/resource/Assets0Images00004.jpg?sv=2017-04-17&sr=b&sig=YIvPBBWHYW%2FUDu2nMNiHOMVJnC37Id1TQQxTsaL9E%2F4%3D&spr=https&se=2022-12-30T16%3A52%3A12Z&sp=r",
    "guild_supply": "https://docserverpwaprodcin.blob.core.windows.net/9b341c64-9324-42f1-b8c8-41b3bb579549-1/resource/Assets0Images00005.jpg?sv=2017-04-17&sr=b&sig=YnmaFJz%2BBpHevBasDOvYqJrkGS%2FJN5whpNWBdGDFnFU%3D&spr=https&se=2022-12-30T16%3A52%3A12Z&sp=r",
    "guild_wealth": "https://docserverpwaprodcin.blob.core.windows.net/9b341c64-9324-42f1-b8c8-41b3bb579549-1/resource/Assets0Images00006.jpg?sv=2017-04-17&sr=b&sig=CP6M1v3l9BtNd0k0yPfTOFHZG7agJ0peXGl%2Fv2oeAvM%3D&spr=https&se=2022-12-30T16%3A52%3A12Z&sp=r",
    "Harshal Jawale": "https://docserverpwaprodcin.blob.core.windows.net/9b341c64-9324-42f1-b8c8-41b3bb579549-1/resource/Assets0Images00007.jpg?sv=2017-04-17&sr=b&sig=whVIoJewqFaNyWlyYJRZHmNQSmSTUP6nV%2B3bS6aB874%3D&spr=https&se=2022-12-30T16%3A52%3A12Z&sp=r",
    "Image": "https://docserverpwaprodcin.blob.core.windows.net/9b341c64-9324-42f1-b8c8-41b3bb579549-1/resource/Assets0Images00010.jpeg?sv=2017-04-17&sr=b&sig=YcPzoptLug%2Bq89fqEz25SJinC4gyymyzlUBgXhn1PNM%3D&spr=https&se=2022-12-30T16%3A52%3A12Z&sp=r",
    "Image (1)": "https://docserverpwaprodcin.blob.core.windows.net/9b341c64-9324-42f1-b8c8-41b3bb579549-1/resource/Assets0Images00008.jpeg?sv=2017-04-17&sr=b&sig=og4cLnKm2aWA4aTCPi7zH4sPYrf14bnD6FXB1HzX%2FnU%3D&spr=https&se=2022-12-30T16%3A52%3A12Z&sp=r",
    "Image (2)": "https://docserverpwaprodcin.blob.core.windows.net/9b341c64-9324-42f1-b8c8-41b3bb579549-1/resource/Assets0Images00009.jpeg?sv=2017-04-17&sr=b&sig=UpeKo7fwpKHjRI8sSKI%2Fpanv27qYHxKLhuUsoFnBYGk%3D&spr=https&se=2022-12-30T16%3A52%3A12Z&sp=r",
    "Image1_2": "https://docserverpwaprodcin.blob.core.windows.net/9b341c64-9324-42f1-b8c8-41b3bb579549-1/resource/Assets0Images00011.jpeg?sv=2017-04-17&sr=b&sig=lo5yZuz6iF2iJbqEcksuQ7fV2Q2bvkmiZnLedz98964%3D&spr=https&se=2022-12-30T16%3A52%3A12Z&sp=r",
    "Image2_2": "https://docserverpwaprodcin.blob.core.windows.net/9b341c64-9324-42f1-b8c8-41b3bb579549-1/resource/Assets0Images00012.jpeg?sv=2017-04-17&sr=b&sig=8OISqWq2C4XAv1J8RO03MI%2BDxE5IJeWROD9YzbVYALY%3D&spr=https&se=2022-12-30T16%3A52%3A12Z&sp=r",
    "jayakanth abhimanyu": "https://docserverpwaprodcin.blob.core.windows.net/9b341c64-9324-42f1-b8c8-41b3bb579549-1/resource/Assets0Images00013.jpg?sv=2017-04-17&sr=b&sig=TUEUeFEzJCcLMZEP9K%2FVhb4k2%2F3wdYbqtSLljxgV8JU%3D&spr=https&se=2022-12-30T16%3A52%3A12Z&sp=r",
    "linkedin": "https://docserverpwaprodcin.blob.core.windows.net/9b341c64-9324-42f1-b8c8-41b3bb579549-1/resource/Assets0Images00014.svg?sv=2017-04-17&sr=b&sig=rlm9DuUvRpNm%2Brz7ErlaS70ZdSV%2FyYFKCuruOjETQCs%3D&spr=https&se=2022-12-30T16%3A52%3A12Z&sp=r",
    "logo": "https://docserverpwaprodcin.blob.core.windows.net/9b341c64-9324-42f1-b8c8-41b3bb579549-1/resource/Assets0Images00015.jpg?sv=2017-04-17&sr=b&sig=fB%2FHat78bklpcIINn%2FToVaLjFrFTG5GbDj8Wy12c7bU%3D&spr=https&se=2022-12-30T16%3A52%3A12Z&sp=r",
    "MicrosoftTeams-image (1)": "https://docserverpwaprodcin.blob.core.windows.net/9b341c64-9324-42f1-b8c8-41b3bb579549-1/resource/Assets0Images00016.png?sv=2017-04-17&sr=b&sig=Zm%2FbQatNSthbKHROcClckbAKMRPoWp166S8f7ulKgQw%3D&spr=https&se=2022-12-30T16%3A52%3A12Z&sp=r",
    "MicrosoftTeams-image (2)": "https://docserverpwaprodcin.blob.core.windows.net/9b341c64-9324-42f1-b8c8-41b3bb579549-1/resource/Assets0Images00017.png?sv=2017-04-17&sr=b&sig=vc56UNxGjbZ6y4RgZspeyUyoc7m82aspPv9GrD70JQA%3D&spr=https&se=2022-12-30T16%3A52%3A12Z&sp=r",
    "MicrosoftTeams-image (3)": "https://docserverpwaprodcin.blob.core.windows.net/9b341c64-9324-42f1-b8c8-41b3bb579549-1/resource/Assets0Images00018.png?sv=2017-04-17&sr=b&sig=Ld3uZ4ZArms9azAVz%2FaXurO7RmsV2hgr7xIVZI7aKOg%3D&spr=https&se=2022-12-30T16%3A52%3A12Z&sp=r",
    "poojatest": "https://docserverpwaprodcin.blob.core.windows.net/9b341c64-9324-42f1-b8c8-41b3bb579549-1/resource/Assets0Images00019.PNG?sv=2017-04-17&sr=b&sig=3E2iB%2F8w%2BxcCm4%2FFAHJthwTHNT6zn5b0LzScVgTH1eg%3D&spr=https&se=2022-12-30T16%3A52%3A12Z&sp=r",
    "poojatest1": "https://docserverpwaprodcin.blob.core.windows.net/9b341c64-9324-42f1-b8c8-41b3bb579549-1/resource/Assets0Images00020.png?sv=2017-04-17&sr=b&sig=JSCQ9OtOhzJgGOiS2lZ20hsR7lLNg%2FfyDlDTw1lETqQ%3D&spr=https&se=2022-12-30T16%3A52%3A12Z&sp=r",
    "priya": "https://docserverpwaprodcin.blob.core.windows.net/9b341c64-9324-42f1-b8c8-41b3bb579549-1/resource/Assets0Images00021.PNG?sv=2017-04-17&sr=b&sig=6cNPYkxzhAvpt%2BZBMVTAwfYgP9UmUJ1XWCfhdX5VHjo%3D&spr=https&se=2022-12-30T16%3A52%3A12Z&sp=r",
    "priyatest": "https://docserverpwaprodcin.blob.core.windows.net/9b341c64-9324-42f1-b8c8-41b3bb579549-1/resource/Assets0Images00022.PNG?sv=2017-04-17&sr=b&sig=zmkYw6HotJE%2BYERWE03wvrjOoStye7lfozdggjDBjUY%3D&spr=https&se=2022-12-30T16%3A52%3A12Z&sp=r",
    "priyatest1": "https://docserverpwaprodcin.blob.core.windows.net/9b341c64-9324-42f1-b8c8-41b3bb579549-1/resource/Assets0Images00023.png?sv=2017-04-17&sr=b&sig=huMOEADrvubxfaN09sxSZbMqH2c4byeF71Zrt79wZzY%3D&spr=https&se=2022-12-30T16%3A52%3A12Z&sp=r",
    "Quotes1": "https://docserverpwaprodcin.blob.core.windows.net/9b341c64-9324-42f1-b8c8-41b3bb579549-1/resource/Assets0Images00024.png?sv=2017-04-17&sr=b&sig=gvlBsx9WZs8EHeifgPoa99LqRCHTYhaALl1uuTi1VEw%3D&spr=https&se=2022-12-30T16%3A52%3A12Z&sp=r",
    "Quotes2": "https://docserverpwaprodcin.blob.core.windows.net/9b341c64-9324-42f1-b8c8-41b3bb579549-1/resource/Assets0Images00025.png?sv=2017-04-17&sr=b&sig=Y%2Fpz4LSOmH9hV57pEy2Y8wL459F6UUPWVraFyVvaGvA%3D&spr=https&se=2022-12-30T16%3A52%3A12Z&sp=r",
    "Rohan Kudav": "https://docserverpwaprodcin.blob.core.windows.net/9b341c64-9324-42f1-b8c8-41b3bb579549-1/resource/Assets0Images00026.jpg?sv=2017-04-17&sr=b&sig=lclfolfeLA7zhAMckabooVUo55EwEkMkKERWyv3RflE%3D&spr=https&se=2022-12-30T16%3A52%3A12Z&sp=r",
    "sanjeev korupolu": "https://docserverpwaprodcin.blob.core.windows.net/9b341c64-9324-42f1-b8c8-41b3bb579549-1/resource/Assets0Images00027.jpg?sv=2017-04-17&sr=b&sig=7P8axA%2FiW1g6oRIBNLc36msxBlETxtKjKuEfmBK8Oes%3D&spr=https&se=2022-12-30T16%3A52%3A12Z&sp=r",
    "soundarya cholkar": "https://docserverpwaprodcin.blob.core.windows.net/9b341c64-9324-42f1-b8c8-41b3bb579549-1/resource/Assets0Images00028.jpg?sv=2017-04-17&sr=b&sig=0ixkq1zeAM%2FQ6F9Ra%2Fmjnra0vfUp4IhIh3fTQWo%2B%2B38%3D&spr=https&se=2022-12-30T16%3A52%3A12Z&sp=r",
    "square-facebook": "https://docserverpwaprodcin.blob.core.windows.net/9b341c64-9324-42f1-b8c8-41b3bb579549-1/resource/Assets0Images00029.svg?sv=2017-04-17&sr=b&sig=Vu2Qk4ZN%2BrUUvVmM%2BS5S6wmxiy9O2zwY8jW5Oa%2BQcmY%3D&spr=https&se=2022-12-30T16%3A52%3A12Z&sp=r",
    "square-twitter": "https://docserverpwaprodcin.blob.core.windows.net/9b341c64-9324-42f1-b8c8-41b3bb579549-1/resource/Assets0Images00030.svg?sv=2017-04-17&sr=b&sig=%2BquxLbMss%2BhjLQbU1q%2B387rdF1BcxXRlC6RwCQprc7Q%3D&spr=https&se=2022-12-30T16%3A52%3A12Z&sp=r",
    "testomonial": "https://docserverpwaprodcin.blob.core.windows.net/9b341c64-9324-42f1-b8c8-41b3bb579549-1/resource/Assets0Images00031.PNG?sv=2017-04-17&sr=b&sig=5CkV4n8Ov3lwEZ1cY53a99qUwtcqJKnVkOIYmyUYGWc%3D&spr=https&se=2022-12-30T16%3A52%3A12Z&sp=r",
    "youtube": "https://docserverpwaprodcin.blob.core.windows.net/9b341c64-9324-42f1-b8c8-41b3bb579549-1/resource/Assets0Images00032.svg?sv=2017-04-17&sr=b&sig=O1SSul2bOCJ9ngqBpZZHORAaSQvbf6GVGrIuxLXmet8%3D&spr=https&se=2022-12-30T16%3A52%3A12Z&sp=r"
  },
  "OrderComponentMetadata": {
    "0927d2b0e1b146c68bb9d9479edc1044": 3,
    "62dc4f1561b4448e901618e4647b41b4": 0,
    "923589e162334ba3ac42a49447cb3358": 5,
    "abc5859afff742348a300a44f7269761": 1,
    "f210c8996a1c4890ba04d40592a3d7d0": 2,
    "f519ced9060241e4947d9bc36dcc7f62": 4
  },
  "OrderComponentTemplate": {
    "0927d2b0e1b146c68bb9d9479edc1044": 3,
    "62dc4f1561b4448e901618e4647b41b4": 0,
    "923589e162334ba3ac42a49447cb3358": 5,
    "abc5859afff742348a300a44f7269761": 1,
    "f210c8996a1c4890ba04d40592a3d7d0": 2,
    "f519ced9060241e4947d9bc36dcc7f62": 4
  },
  "OrderDataSource": {
    "Activities": 36,
    "Activity": 10,
    "Blog": 11,
    "Blog_1": 12,
    "BlogComments": 37,
    "BlogsPerMonth": 38,
    "colHorizontalMenu": 39,
    "ColumnChartSample": 13,
    "ComboBoxSample": 14,
    "Comment": 15,
    "Community_1": 16,
    "Community_2": 17,
    "CommunityEvents": 40,
    "CustomGallerySample": 18,
    "DropdownColumn": 41,
    "DropDownSample": 19,
    "Environment Variable Values": 35,
    "Environment Variable Values\\componentstate": 6,
    "Environment Variable Values\\default.cds_environmentvariablevalue_views": 9,
    "Environment Variable Values\\environmentvariablevalue_statecode": 7,
    "Environment Variable Values\\environmentvariablevalue_statuscode": 8,
    "Environment Variable Values\\ismanaged": 5,
    "Event": 21,
    "Event Track Details": 20,
    "EventCal": 61,
    "EventCategories": 42,
    "EventsByPillars": 43,
    "EventStatus": 44,
    "EventStatusAdmin": 45,
    "EventTitle": 46,
    "GetDataURI": 0,
    "GroupUsers": 47,
    "GroupUsersByGuild": 48,
    "Guild": 25,
    "Guild List": 22,
    "Guild List_1": 24,
    "Guild List1": 23,
    "Guild_1": 26,
    "GuildCommunities": 49,
    "GuildEvents": 60,
    "Hours": 50,
    "LegendSample": 27,
    "Like": 28,
    "LineChartSample": 29,
    "ListboxSample": 30,
    "Office365Outlook": 1,
    "Office365Users": 2,
    "Office365Users_1": 3,
    "PieChartSample": 31,
    "Points": 32,
    "Ranks": 51,
    "TopFiveCommunities": 52,
    "TopFivePopularGuilds": 53,
    "TopFiveUsers": 54,
    "UploadFileToDocumentLibrary": 4,
    "User": 33,
    "UserBlog": 55,
    "UserBlogsPerMonth": 56,
    "UserCommunity": 57,
    "UserGuild": 58,
    "userprofile": 59,
    "white_papers": 34
  },
  "OrderGroupControls": {
    "CompositeColumnChart1": {
      "ColumnChart1": 1,
      "Legend2": 2,
      "Title3": 0
    },
    "CompositeColumnChart2": {
      "ColumnChart2": 1,
      "Legend4": 2,
      "Title5": 0
    },
    "CompositeColumnChart2_1": {
      "Legend5_1": 2,
      "Title5_2": 0,
      "Top Communities_1": 1
    },
    "CompositeColumnChart3": {
      "ColumnChart4": 1,
      "Title6": 0
    },
    "CompositeColumnChart4": {
      "ColumnChart3": 1,
      "Legend10": 2,
      "Title11_1": 0
    },
    "CompositeColumnChart5": {
      "ColumnChart5": 1,
      "Title9": 0
    },
    "CompositeLineChart1": {
      "Legend1": 2,
      "LineChart1": 1,
      "Title2": 0
    },
    "CompositeLineChart1_1": {
      "Legend1_1": 2,
      "LineChart1_1": 1,
      "Title1_1": 0
    },
    "CompositeLineChart2": {
      "Legend6_1": 2,
      "LineChart2": 1,
      "Title7": 0
    },
    "CompositePieChart3": {
      "Legend6": 2,
      "PieChart3": 1,
      "Title8": 0
    },
    "CompositePieChart4": {
      "Legend9": 2,
      "PieChart4": 1,
      "Title10_1": 0
    },
    "CompositePieChart5": {
      "Legend8": 2,
      "PieChart5": 1,
      "Title10": 0
    },
    "DtopDownDash": {
      "Button5": 1,
      "Rectangle6": 0
    },
    "DtopDownDash_1": {
      "Button5_4": 1,
      "Rectangle6_1": 0
    },
    "DtopDownDash_2": {
      "Button5_5": 1,
      "Rectangle6_2": 0
    },
    "Group1": {
      "Icon9": 5,
      "Image14": 1,
      "Image14_1": 2,
      "Image14_2": 3,
      "Label8": 4,
      "Rectangle4": 0
    },
    "HomeDropDown": {
      "Button1": 1,
      "Button1_2": 2,
      "Button1_3": 3,
      "Button1_4": 4,
      "Button1_5": 5,
      "Rectangle3": 0
    },
    "NavBarGr": {
      "Button17": 2,
      "Button18": 3,
      "Button18_1": 4,
      "Button18_2": 5,
      "Button18_3": 6,
      "Button20_1": 8,
      "Button20_5": 9,
      "Component1_1": 0,
      "Icon3": 7,
      "Rectangle2": 1
    },
    "NavBarGr_1": {
      "Button17_1": 2,
      "Button18_4": 6,
      "Button18_5": 5,
      "Button18_6": 4,
      "Button18_7": 3,
      "Button20_10": 10,
      "Button20_11": 8,
      "Button20_12": 9,
      "Component1_3": 0,
      "Icon3_2": 7,
      "Rectangle2_1": 1
    },
    "NavBarGr_2": {
      "Button17_3": 2,
      "Button18_12": 6,
      "Button18_13": 5,
      "Button18_14": 4,
      "Button18_15": 3,
      "Button20_3": 8,
      "Button20_6": 9,
      "Component1_4": 0,
      "Icon3_3": 7,
      "Rectangle2_3": 1
    },
    "NavBarGr_3": {
      "Button17_4": 2,
      "Button18_16": 6,
      "Button18_17": 5,
      "Button18_18": 4,
      "Button18_19": 3,
      "Button20_7": 9,
      "Button20_8": 8,
      "Component1_2": 0,
      "Icon3_1": 7,
      "Rectangle2_4": 1
    }
  },
  "OrderPcfTemplate": {},
  "OrderTemplate": {},
  "OrderXMLTemplate": {
    "addMedia": 19,
    "arrow": 21,
    "attachments": 7,
    "barChart": 12,
    "button": 5,
    "circle": 16,
    "datepicker": 10,
    "dropdown": 8,
    "fluidGrid": 3,
    "form": 6,
    "gallery": 11,
    "groupContainer": 15,
    "htmlViewer": 20,
    "icon": 2,
    "image": 4,
    "label": 1,
    "legend": 14,
    "lineChart": 13,
    "microsoftStreamPlayback": 22,
    "pdfViewer": 25,
    "pieChart": 17,
    "rectangle": 0,
    "richTextEditor": 18,
    "star": 24,
    "text": 9,
    "timer": 23
  },
  "OverridablePropertiesEntry": {
    "About": {},
    "ActivityDetails": {},
    "AddActivity": {},
    "AddPicture1": {},
    "AddPicture10": {},
    "AddPicture2": {},
    "AddPicture3": {},
    "AddPicture5": {},
    "AddPicture5_1": {},
    "AddPicture6": {},
    "AddPicture7": {},
    "AddPicture8": {},
    "AddPicture9": {},
    "Admin": {},
    "allBlogs": {},
    "AllBlogs": {},
    "App": {},
    "Attachments_DataCard1": {},
    "Attachments_DataCard2": {},
    "Attachments_DataCard2_1": {},
    "Attachments_DataCard2_2": {},
    "Attachments_DataCard4": {},
    "Body1_1": {},
    "Body2": {},
    "btnNext": {},
    "btnPrevious": {},
    "Button1": {},
    "Button1_1": {},
    "Button1_2": {},
    "Button1_3": {},
    "Button1_4": {},
    "Button1_5": {},
    "Button10": {},
    "Button11": {},
    "Button12": {},
    "Button13": {},
    "Button14": {},
    "Button15": {},
    "Button16": {},
    "Button16_1": {},
    "Button17": {},
    "Button17_1": {},
    "Button17_3": {},
    "Button17_4": {},
    "Button18": {},
    "Button18_1": {},
    "Button18_12": {},
    "Button18_13": {},
    "Button18_14": {},
    "Button18_15": {},
    "Button18_16": {},
    "Button18_17": {},
    "Button18_18": {},
    "Button18_19": {},
    "Button18_2": {},
    "Button18_3": {},
    "Button18_4": {},
    "Button18_5": {},
    "Button18_6": {},
    "Button18_7": {},
    "Button2": {},
    "Button2_3": {},
    "Button2_4": {},
    "Button2_5": {},
    "Button2_6": {},
    "Button20_1": {},
    "Button20_10": {},
    "Button20_11": {},
    "Button20_12": {},
    "Button20_3": {},
    "Button20_5": {},
    "Button20_6": {},
    "Button20_7": {},
    "Button20_8": {},
    "Button3": {},
    "Button3_1": {},
    "Button4": {},
    "Button4_1": {},
    "Button5": {},
    "Button5_1": {},
    "Button5_2": {},
    "Button5_3": {},
    "Button5_4": {},
    "Button5_5": {},
    "Button6": {},
    "Button6_1": {},
    "Button7": {},
    "Button8": {},
    "Button8_1": {},
    "Button8_2": {},
    "Button9": {},
    "Canvas1": {},
    "Canvas1_1": {},
    "Canvas10": {},
    "Canvas11": {},
    "Canvas12": {},
    "Canvas2": {},
    "Canvas3": {},
    "Canvas4": {},
    "Canvas5": {},
    "Canvas6": {},
    "Canvas7": {},
    "Canvas8": {},
    "Canvas9": {},
    "Category_Column1": {},
    "Circle1_1": {},
    "ColumnChart1": {},
    "ColumnChart2": {},
    "ColumnChart3": {},
    "ColumnChart4": {},
    "ColumnChart5": {},
    "Communities_Column1_1": {},
    "Community": {},
    "CommunityRole_Column1_1": {},
    "Component1": {},
    "Component1_1": {},
    "Component1_2": {},
    "Component1_3": {},
    "Component1_4": {},
    "Component2_1": {},
    "Component3_1": {},
    "CompositeColumnChart1": {},
    "CompositeColumnChart2": {},
    "CompositeColumnChart2_1": {},
    "CompositeColumnChart3": {},
    "CompositeColumnChart4": {},
    "CompositeColumnChart5": {},
    "CompositeLineChart1": {},
    "CompositeLineChart1_1": {},
    "CompositeLineChart2": {},
    "CompositePieChart3": {},
    "CompositePieChart4": {},
    "CompositePieChart5": {},
    "Container1": {},
    "Container2": {},
    "Container3": {},
    "Container5": {},
    "content": {},
    "content_1": {},
    "Count_Column1": {},
    "createBlog": {},
    "Dashboard": {},
    "DataCard1": {},
    "DataCard10": {},
    "DataCard11": {},
    "DataCard12": {},
    "DataCard13": {},
    "DataCard14": {},
    "DataCard15": {},
    "DataCard16": {},
    "DataCard17": {},
    "DataCard18": {},
    "DataCard19": {},
    "DataCard2": {},
    "DataCard2_1": {},
    "DataCard20": {},
    "DataCard21": {},
    "DataCard22": {},
    "DataCard23": {},
    "DataCard24": {},
    "DataCard25": {},
    "DataCard26": {},
    "DataCard27": {},
    "DataCard28": {},
    "DataCard29": {},
    "DataCard3": {},
    "DataCard30": {},
    "DataCard31": {},
    "DataCard32": {},
    "DataCard33": {},
    "DataCard34": {},
    "DataCard35": {},
    "DataCard4": {},
    "DataCard5": {},
    "DataCard6": {},
    "DataCard7": {},
    "DataCard8": {},
    "DataCard9": {},
    "DataCardKey1": {},
    "DataCardKey10": {},
    "DataCardKey11": {},
    "DataCardKey12": {},
    "DataCardKey13": {},
    "DataCardKey14": {},
    "DataCardKey15": {},
    "DataCardKey17": {},
    "DataCardKey18": {},
    "DataCardKey18_1": {},
    "DataCardKey19": {},
    "DataCardKey2": {},
    "DataCardKey20": {},
    "DataCardKey22": {},
    "DataCardKey23": {},
    "DataCardKey24": {},
    "DataCardKey25": {},
    "DataCardKey26": {},
    "DataCardKey27": {},
    "DataCardKey29": {},
    "DataCardKey3": {},
    "DataCardKey31": {},
    "DataCardKey32": {},
    "DataCardKey33": {},
    "DataCardKey34": {},
    "DataCardKey35": {},
    "DataCardKey4": {},
    "DataCardKey4_1": {},
    "DataCardKey43": {},
    "DataCardKey5": {},
    "DataCardKey6": {},
    "DataCardKey6_1": {},
    "DataCardKey7": {},
    "DataCardKey8": {},
    "DataCardKey9": {},
    "DataCardValue1": {},
    "DataCardValue11": {},
    "DataCardValue12": {},
    "DataCardValue13": {},
    "DataCardValue14": {},
    "DataCardValue15": {},
    "DataCardValue16": {},
    "DataCardValue17": {},
    "DataCardValue17_1": {},
    "DataCardValue18": {},
    "DataCardValue2": {},
    "DataCardValue20": {},
    "DataCardValue21": {},
    "DataCardValue23": {},
    "DataCardValue25": {},
    "DataCardValue26": {},
    "DataCardValue27": {},
    "DataCardValue28": {},
    "DataCardValue3_1": {},
    "DataCardValue31": {},
    "DataCardValue4_1": {},
    "DataCardValue42": {},
    "DataCardValue5_1": {},
    "DataCardValue8": {},
    "DataCardValue8_1": {},
    "DataCardValue9": {},
    "DataTable1": {},
    "DataTable1_1": {},
    "DataTable2": {},
    "DataTable3": {},
    "DataTable3_1": {},
    "DataTable4": {},
    "Date_DataCard1": {},
    "Date_DataCard2": {},
    "DateofEvent_Column1_1": {},
    "DatePicker1": {},
    "DatePicker1_1": {},
    "ddPageSize": {},
    "Description_DataCard1": {},
    "Description_DataCard3": {},
    "Designation1_DataCard1": {},
    "detailBlog": {},
    "detailBlog2": {},
    "Dropdown1": {},
    "Dropdown1_1": {},
    "Dropdown2": {},
    "Dropdown2_1": {},
    "Dropdown2_2": {},
    "Dropdown3": {},
    "Dropdown4": {},
    "Dropdown5": {},
    "Dropdown6": {},
    "Dropdown7": {},
    "DtopDownDash": {},
    "DtopDownDash_1": {},
    "DtopDownDash_2": {},
    "editBlog": {},
    "ErrorMessage1": {},
    "ErrorMessage10": {},
    "ErrorMessage11": {},
    "ErrorMessage12": {},
    "ErrorMessage13": {},
    "ErrorMessage14": {},
    "ErrorMessage15": {},
    "ErrorMessage17": {},
    "ErrorMessage18": {},
    "ErrorMessage18_1": {},
    "ErrorMessage19": {},
    "ErrorMessage2": {},
    "ErrorMessage20": {},
    "ErrorMessage22": {},
    "ErrorMessage23": {},
    "ErrorMessage24": {},
    "ErrorMessage25": {},
    "ErrorMessage26": {},
    "ErrorMessage27": {},
    "ErrorMessage29": {},
    "ErrorMessage3": {},
    "ErrorMessage31": {},
    "ErrorMessage32": {},
    "ErrorMessage33": {},
    "ErrorMessage34": {},
    "ErrorMessage35": {},
    "ErrorMessage4": {},
    "ErrorMessage4_1": {},
    "ErrorMessage43": {},
    "ErrorMessage5": {},
    "ErrorMessage6": {},
    "ErrorMessage6_1": {},
    "ErrorMessage7": {},
    "ErrorMessage8": {},
    "ErrorMessage9": {},
    "EventDetails": {},
    "EventEdit": {},
    "EventForm": {},
    "FAQs": {},
    "Feedback": {},
    "Feedback_Column1": {},
    "FileUpload": {},
    "Footer": {},
    "Form1_1": {},
    "Form2": {},
    "Form2_1": {},
    "Form3": {},
    "Form3_1": {},
    "Form3_2": {},
    "Form4": {},
    "Form5": {},
    "FullDescription_DataCard1": {},
    "Gallery1": {},
    "Gallery1_1": {},
    "Gallery11": {},
    "Gallery12": {},
    "Gallery18": {},
    "Gallery18_1": {},
    "Gallery2": {},
    "Gallery2_1": {},
    "Gallery3": {},
    "Gallery4": {},
    "Gallery5": {},
    "Gallery7": {},
    "Gallery9": {},
    "galleryTemplate1": {},
    "galleryTemplate1_1": {},
    "galleryTemplate10": {},
    "galleryTemplate11": {},
    "galleryTemplate12": {},
    "galleryTemplate18": {},
    "galleryTemplate18_1": {},
    "galleryTemplate2": {},
    "galleryTemplate2_1": {},
    "galleryTemplate2_2": {},
    "galleryTemplate3": {},
    "galleryTemplate3_1": {},
    "galleryTemplate4": {},
    "galleryTemplate5": {},
    "galleryTemplate6": {},
    "galleryTemplate7": {},
    "galPaginated": {},
    "Group1": {},
    "Guild Form": {},
    "Guild_DataCard1": {},
    "GuildStats": {},
    "Home": {},
    "HomeDropDown": {},
    "HomeImage": {},
    "HtmlText2": {},
    "HtmlText3": {},
    "Icon1": {},
    "Icon10": {},
    "Icon10_1": {},
    "Icon11": {},
    "Icon12": {},
    "Icon13": {},
    "Icon14": {},
    "Icon15": {},
    "Icon16": {},
    "Icon17": {},
    "Icon18": {},
    "Icon19": {},
    "Icon2": {},
    "Icon20": {},
    "Icon21": {},
    "Icon22": {},
    "Icon23": {},
    "Icon24": {},
    "Icon25": {},
    "Icon26": {},
    "Icon27": {},
    "Icon27_1": {},
    "Icon29": {},
    "Icon3": {},
    "Icon3_1": {},
    "Icon3_2": {},
    "Icon3_3": {},
    "Icon3_4": {},
    "Icon3_5": {},
    "Icon3_6": {},
    "Icon3_7": {},
    "Icon30": {},
    "Icon31": {},
    "Icon32": {},
    "Icon33": {},
    "Icon4": {},
    "Icon4_2": {},
    "Icon5": {},
    "Icon5_1": {},
    "Icon5_2": {},
    "Icon5_3": {},
    "Icon6": {},
    "Icon7": {},
    "Icon7_1": {},
    "Icon8": {},
    "Icon9": {},
    "iconNextMonth1_1": {},
    "iconPrevMonth1_1": {},
    "Image_DataCard1": {},
    "Image_DataCard2": {},
    "Image_DataCard3": {},
    "Image1": {},
    "Image1_1": {},
    "Image1_DataCard1": {},
    "Image10": {},
    "Image10_1": {},
    "Image10_2": {},
    "Image10_3": {},
    "Image10_4": {},
    "Image11": {},
    "Image11_1": {},
    "Image11_2": {},
    "Image11_3": {},
    "Image11_4": {},
    "Image12": {},
    "Image13": {},
    "Image14": {},
    "Image14_1": {},
    "Image14_2": {},
    "Image15": {},
    "Image16": {},
    "Image17": {},
    "Image18": {},
    "Image2": {},
    "Image2_1": {},
    "Image20": {},
    "Image21": {},
    "Image22": {},
    "Image23": {},
    "Image24": {},
    "Image25": {},
    "Image25_1": {},
    "Image25_2": {},
    "Image26": {},
    "Image27": {},
    "Image28": {},
    "Image29": {},
    "Image3": {},
    "Image3_1": {},
    "Image3_2": {},
    "Image30": {},
    "Image31": {},
    "Image34": {},
    "Image4": {},
    "Image4_1": {},
    "Image5": {},
    "Image5_1": {},
    "Image6": {},
    "Image7": {},
    "Image7_1": {},
    "Image8": {},
    "Image8_1": {},
    "Image9": {},
    "Label1": {},
    "Label1_1": {},
    "Label10": {},
    "Label10_1": {},
    "Label11": {},
    "Label11_1": {},
    "Label11_2": {},
    "Label11_3": {},
    "Label11_4": {},
    "Label11_5": {},
    "Label12": {},
    "Label12_1": {},
    "Label12_2": {},
    "Label13": {},
    "Label13_1": {},
    "Label13_2": {},
    "Label14": {},
    "Label15": {},
    "Label16": {},
    "Label16_1": {},
    "Label17": {},
    "Label17_1": {},
    "Label18": {},
    "Label18_1": {},
    "Label19": {},
    "Label2": {},
    "Label2_1": {},
    "Label2_2": {},
    "Label2_4": {},
    "Label2_5": {},
    "Label2_6": {},
    "Label2_7": {},
    "Label20": {},
    "Label21": {},
    "Label21_1": {},
    "Label22": {},
    "Label22_1": {},
    "Label23": {},
    "Label24": {},
    "Label24_1": {},
    "Label25": {},
    "Label26": {},
    "Label26_1": {},
    "Label27": {},
    "Label28": {},
    "Label28_1": {},
    "Label29": {},
    "Label3": {},
    "Label3_1": {},
    "Label3_4": {},
    "Label3_5": {},
    "Label3_6": {},
    "Label3_7": {},
    "Label30": {},
    "Label31": {},
    "Label32": {},
    "Label33": {},
    "Label34": {},
    "Label35": {},
    "Label36": {},
    "Label37": {},
    "Label38": {},
    "Label39": {},
    "Label4": {},
    "Label4_1": {},
    "Label4_3": {},
    "Label40": {},
    "Label41": {},
    "Label42": {},
    "Label43": {},
    "Label44": {},
    "Label45": {},
    "Label46": {},
    "Label47": {},
    "Label48": {},
    "Label49": {},
    "Label5": {},
    "Label5_1": {},
    "Label5_2": {},
    "Label5_3": {},
    "Label6": {},
    "Label6_1": {},
    "Label6_2": {},
    "Label6_3": {},
    "Label6_4": {},
    "Label6_5": {},
    "Label6_7": {},
    "Label7": {},
    "Label7_1": {},
    "Label8": {},
    "Label8_1": {},
    "Label8_2": {},
    "Label9": {},
    "Label9_1": {},
    "Label9_2": {},
    "Label9_3": {},
    "Label9_4": {},
    "Label9_5": {},
    "LblAppName1": {},
    "LblAppName10": {},
    "LblAppName2": {},
    "LblAppName3": {},
    "LblAppName4": {},
    "LblAppName5": {},
    "LblAppName6": {},
    "LblAppName7": {},
    "LblAppName8": {},
    "LblAppName9": {},
    "LblMonthSelected1_1": {},
    "lblPagination": {},
    "Legend1": {},
    "Legend1_1": {},
    "Legend10": {},
    "Legend2": {},
    "Legend4": {},
    "Legend5_1": {},
    "Legend6": {},
    "Legend6_1": {},
    "Legend8": {},
    "Legend9": {},
    "LineChart1": {},
    "LineChart1_1": {},
    "LineChart2": {},
    "Link_DataCard1": {},
    "Members_Column1": {},
    "MicrosoftStream2": {},
    "MonthDayGallery1_1": {},
    "Name_Column1": {},
    "Name_DataCard1": {},
    "NavBar": {},
    "NavBarGr": {},
    "NavBarGr_1": {},
    "NavBarGr_2": {},
    "NavBarGr_3": {},
    "NextArrow2": {},
    "NextArrow20": {},
    "NextArrow20_1": {},
    "NextArrow6": {},
    "No_Column1": {},
    "PdfViewer1": {},
    "PieChart3": {},
    "PieChart4": {},
    "PieChart5": {},
    "Points_Column1": {},
    "Polestar1_DataCard1": {},
    "Profile": {},
    "Rectangle1": {},
    "Rectangle2": {},
    "Rectangle2_1": {},
    "Rectangle2_3": {},
    "Rectangle2_4": {},
    "Rectangle3": {},
    "Rectangle4": {},
    "Rectangle6": {},
    "Rectangle6_1": {},
    "Rectangle6_2": {},
    "Rectangle7": {},
    "Rectangle8": {},
    "RectQuickActionBar1": {},
    "RectQuickActionBar1_2": {},
    "RectQuickActionBar10": {},
    "RectQuickActionBar11": {},
    "RectQuickActionBar12": {},
    "RectQuickActionBar13": {},
    "RectQuickActionBar2": {},
    "RectQuickActionBar3": {},
    "RectQuickActionBar4": {},
    "RectQuickActionBar5": {},
    "RectQuickActionBar6": {},
    "RectQuickActionBar7": {},
    "RectQuickActionBar8": {},
    "RectQuickActionBar9": {},
    "RichTextEditor1": {},
    "Separator1": {},
    "Separator2": {},
    "Separator22": {},
    "Separator22_1": {},
    "Separator4": {},
    "Separator5": {},
    "Separator6_1": {},
    "Separator7": {},
    "Separator9": {},
    "shareIt": {},
    "Short Description_DataCard2": {},
    "Star1_1": {},
    "StarVisible1": {},
    "StarVisible10": {},
    "StarVisible11": {},
    "StarVisible12": {},
    "StarVisible13": {},
    "StarVisible14": {},
    "StarVisible15": {},
    "StarVisible17": {},
    "StarVisible18": {},
    "StarVisible18_1": {},
    "StarVisible19": {},
    "StarVisible2": {},
    "StarVisible20": {},
    "StarVisible22": {},
    "StarVisible23": {},
    "StarVisible24": {},
    "StarVisible25": {},
    "StarVisible26": {},
    "StarVisible27": {},
    "StarVisible29": {},
    "StarVisible3": {},
    "StarVisible31": {},
    "StarVisible32": {},
    "StarVisible33": {},
    "StarVisible34": {},
    "StarVisible35": {},
    "StarVisible4": {},
    "StarVisible4_1": {},
    "StarVisible43": {},
    "StarVisible5": {},
    "StarVisible6": {},
    "StarVisible6_1": {},
    "StarVisible7": {},
    "StarVisible8": {},
    "StarVisible9": {},
    "Subcircle1_1": {},
    "Subtitle1": {},
    "Subtitle2": {},
    "Subtitle20": {},
    "Subtitle20_1": {},
    "Subtitle6": {},
    "Subtitle7": {},
    "Subtitle7_1": {},
    "Subtitle8": {},
    "TextInput1": {},
    "TextInput1_1": {},
    "TextInput10": {},
    "TextInput11": {},
    "TextInput2": {},
    "TextInput3": {},
    "TextInput3_1": {},
    "TextInput3_2": {},
    "TextInput4": {},
    "TextInput4_1": {},
    "TextInput5": {},
    "TextInput6": {},
    "TextInput7": {},
    "TextInput9": {},
    "TextInput9_1": {},
    "Timer1": {},
    "title": {},
    "title_1": {},
    "Title_Column1": {},
    "Title_Column2_1": {},
    "Title_DataCard1": {},
    "Title_DataCard2": {},
    "Title_DataCard4": {},
    "Title1": {},
    "Title1_1": {},
    "Title1_2": {},
    "Title10": {},
    "Title10_1": {},
    "Title11": {},
    "Title11_1": {},
    "Title13": {},
    "Title14": {},
    "Title15": {},
    "Title18": {},
    "Title2": {},
    "Title2_1": {},
    "Title2_2": {},
    "Title26": {},
    "Title26_1": {},
    "Title3": {},
    "Title3_1": {},
    "Title4": {},
    "Title5": {},
    "Title5_2": {},
    "Title6": {},
    "Title7": {},
    "Title8": {},
    "Title8_1": {},
    "Title9": {},
    "Top Communities_1": {},
    "Torch Bearers1_DataCard1": {},
    "Torch Bearers2_DataCard1": {},
    "Torch Bearers3_DataCard1": {},
    "TorchImage1_DataCard1": {},
    "TorchImage2_DataCard1": {},
    "TorchImage3_DataCard1": {},
    "Trend Setters1_DataCard1": {},
    "Trend Setters2_DataCard1": {},
    "Trend Setters3_DataCard2": {},
    "TrendImage1_DataCard1": {},
    "TrendImage2_DataCard1": {},
    "TrendImage3_DataCard1": {},
    "UpcomingGuild": {},
    "UpcomingGuild_1": {},
    "UserName": {},
    "UserName_1": {},
    "UserName_Column1": {},
    "WeekdayGallery1_1": {},
    "WhitePapers": {}
  },
  "PCFDynamicSchemaForIRRetrievalEntry": {},
  "PublishOrderIndices": {
    "About": 1,
    "ActivityDetails": 42,
    "AddActivity": 73,
    "AddPicture1": 149,
    "AddPicture10": 194,
    "AddPicture2": 303,
    "AddPicture3": 397,
    "AddPicture5": 155,
    "AddPicture5_1": 128,
    "AddPicture6": 200,
    "AddPicture7": 161,
    "AddPicture8": 182,
    "AddPicture9": 188,
    "Admin": 110,
    "allBlogs": 163,
    "AllBlogs": 201,
    "App": 0,
    "Attachments_DataCard1": 202,
    "Attachments_DataCard2": 475,
    "Attachments_DataCard2_1": 588,
    "Attachments_DataCard2_2": 660,
    "Attachments_DataCard4": 230,
    "Body1_1": 527,
    "Body2": 452,
    "btnNext": 34,
    "btnPrevious": 33,
    "Button1": 90,
    "Button1_1": 485,
    "Button1_2": 67,
    "Button1_3": 95,
    "Button1_4": 83,
    "Button1_5": 74,
    "Button10": 385,
    "Button11": 332,
    "Button12": 724,
    "Button13": 279,
    "Button14": 481,
    "Button15": 242,
    "Button16": 727,
    "Button16_1": 726,
    "Button17": 71,
    "Button17_1": 434,
    "Button17_3": 549,
    "Button17_4": 325,
    "Button18": 73,
    "Button18_1": 82,
    "Button18_12": 553,
    "Button18_13": 552,
    "Button18_14": 551,
    "Button18_15": 550,
    "Button18_16": 344,
    "Button18_17": 336,
    "Button18_18": 335,
    "Button18_19": 330,
    "Button18_2": 84,
    "Button18_3": 86,
    "Button18_4": 438,
    "Button18_5": 437,
    "Button18_6": 436,
    "Button18_7": 435,
    "Button2": 341,
    "Button2_3": 707,
    "Button2_4": 498,
    "Button2_5": 705,
    "Button2_6": 706,
    "Button20_1": 4,
    "Button20_10": 402,
    "Button20_11": 403,
    "Button20_12": 401,
    "Button20_3": 506,
    "Button20_5": 3,
    "Button20_6": 505,
    "Button20_7": 311,
    "Button20_8": 312,
    "Button3": 702,
    "Button3_1": 525,
    "Button4": 235,
    "Button4_1": 524,
    "Button5": 72,
    "Button5_1": 562,
    "Button5_2": 596,
    "Button5_3": 207,
    "Button5_4": 511,
    "Button5_5": 326,
    "Button6": 307,
    "Button6_1": 586,
    "Button7": 377,
    "Button8": 378,
    "Button8_1": 526,
    "Button8_2": 665,
    "Button9": 445,
    "Canvas1": 9,
    "Canvas1_1": 243,
    "Canvas10": 597,
    "Canvas11": 639,
    "Canvas12": 675,
    "Canvas2": 236,
    "Canvas3": 442,
    "Canvas4": 291,
    "Canvas5": 406,
    "Canvas6": 512,
    "Canvas7": 350,
    "Canvas8": 382,
    "Canvas9": 566,
    "Category_Column1": 680,
    "Circle1_1": 287,
    "ColumnChart1": 413,
    "ColumnChart2": 422,
    "ColumnChart3": 618,
    "ColumnChart4": 696,
    "ColumnChart5": 695,
    "Communities_Column1_1": 634,
    "Community": 207,
    "CommunityRole_Column1_1": 635,
    "Component1": 9,
    "Component1_1": 1,
    "Component1_2": 309,
    "Component1_3": 400,
    "Component1_4": 503,
    "Component2_1": 11,
    "Component3_1": 14,
    "CompositeColumnChart1": 411,
    "CompositeColumnChart2": 419,
    "CompositeColumnChart2_1": 531,
    "CompositeColumnChart3": 691,
    "CompositeColumnChart4": 614,
    "CompositeColumnChart5": 693,
    "CompositeLineChart1": 408,
    "CompositeLineChart1_1": 534,
    "CompositeLineChart2": 612,
    "CompositePieChart3": 420,
    "CompositePieChart4": 613,
    "CompositePieChart5": 426,
    "Container1": 708,
    "Container2": 315,
    "Container3": 75,
    "Container5": 55,
    "content": 298,
    "content_1": 391,
    "Count_Column1": 681,
    "createBlog": 249,
    "Dashboard": 270,
    "DataCard1": 43,
    "DataCard10": 292,
    "DataCard11": 407,
    "DataCard12": 416,
    "DataCard13": 13,
    "DataCard14": 358,
    "DataCard15": 383,
    "DataCard16": 425,
    "DataCard17": 360,
    "DataCard18": 443,
    "DataCard19": 513,
    "DataCard2": 17,
    "DataCard2_1": 244,
    "DataCard20": 367,
    "DataCard21": 356,
    "DataCard22": 529,
    "DataCard23": 251,
    "DataCard24": 567,
    "DataCard25": 259,
    "DataCard26": 690,
    "DataCard27": 598,
    "DataCard28": 640,
    "DataCard29": 611,
    "DataCard3": 40,
    "DataCard30": 624,
    "DataCard31": 631,
    "DataCard32": 543,
    "DataCard33": 266,
    "DataCard34": 676,
    "DataCard35": 682,
    "DataCard4": 47,
    "DataCard5": 50,
    "DataCard6": 37,
    "DataCard7": 237,
    "DataCard8": 10,
    "DataCard9": 351,
    "DataCardKey1": 101,
    "DataCardKey10": 192,
    "DataCardKey11": 132,
    "DataCardKey12": 137,
    "DataCardKey13": 217,
    "DataCardKey14": 126,
    "DataCardKey15": 198,
    "DataCardKey17": 204,
    "DataCardKey18": 457,
    "DataCardKey18_1": 662,
    "DataCardKey19": 212,
    "DataCardKey2": 147,
    "DataCardKey20": 222,
    "DataCardKey22": 227,
    "DataCardKey23": 232,
    "DataCardKey24": 462,
    "DataCardKey25": 467,
    "DataCardKey26": 472,
    "DataCardKey27": 477,
    "DataCardKey29": 170,
    "DataCardKey3": 106,
    "DataCardKey31": 142,
    "DataCardKey32": 669,
    "DataCardKey33": 111,
    "DataCardKey34": 165,
    "DataCardKey35": 175,
    "DataCardKey4": 153,
    "DataCardKey4_1": 116,
    "DataCardKey43": 591,
    "DataCardKey5": 395,
    "DataCardKey6": 159,
    "DataCardKey6_1": 121,
    "DataCardKey7": 305,
    "DataCardKey8": 180,
    "DataCardKey9": 186,
    "DataCardValue1": 102,
    "DataCardValue11": 205,
    "DataCardValue12": 458,
    "DataCardValue13": 463,
    "DataCardValue14": 468,
    "DataCardValue15": 473,
    "DataCardValue16": 478,
    "DataCardValue17": 213,
    "DataCardValue17_1": 663,
    "DataCardValue18": 223,
    "DataCardValue2": 218,
    "DataCardValue20": 228,
    "DataCardValue21": 233,
    "DataCardValue23": 171,
    "DataCardValue25": 143,
    "DataCardValue26": 112,
    "DataCardValue27": 166,
    "DataCardValue28": 176,
    "DataCardValue3_1": 107,
    "DataCardValue31": 668,
    "DataCardValue4_1": 117,
    "DataCardValue42": 589,
    "DataCardValue5_1": 122,
    "DataCardValue8": 133,
    "DataCardValue8_1": 497,
    "DataCardValue9": 138,
    "DataTable1": 428,
    "DataTable1_1": 633,
    "DataTable2": 540,
    "DataTable3": 545,
    "DataTable3_1": 627,
    "DataTable4": 679,
    "Date_DataCard1": 470,
    "Date_DataCard2": 225,
    "DateofEvent_Column1_1": 629,
    "DatePicker1": 559,
    "DatePicker1_1": 650,
    "ddPageSize": 25,
    "Description_DataCard1": 460,
    "Description_DataCard3": 220,
    "Designation1_DataCard1": 119,
    "detailBlog": 311,
    "detailBlog2": 346,
    "Dropdown1": 334,
    "Dropdown1_1": 626,
    "Dropdown2": 296,
    "Dropdown2_1": 389,
    "Dropdown2_2": 644,
    "Dropdown3": 645,
    "Dropdown4": 651,
    "Dropdown5": 656,
    "Dropdown6": 517,
    "Dropdown7": 678,
    "DtopDownDash": 69,
    "DtopDownDash_1": 510,
    "DtopDownDash_2": 327,
    "editBlog": 348,
    "ErrorMessage1": 103,
    "ErrorMessage10": 195,
    "ErrorMessage11": 134,
    "ErrorMessage12": 139,
    "ErrorMessage13": 219,
    "ErrorMessage14": 129,
    "ErrorMessage15": 201,
    "ErrorMessage17": 206,
    "ErrorMessage18": 459,
    "ErrorMessage18_1": 664,
    "ErrorMessage19": 214,
    "ErrorMessage2": 150,
    "ErrorMessage20": 224,
    "ErrorMessage22": 229,
    "ErrorMessage23": 234,
    "ErrorMessage24": 464,
    "ErrorMessage25": 469,
    "ErrorMessage26": 474,
    "ErrorMessage27": 479,
    "ErrorMessage29": 172,
    "ErrorMessage3": 108,
    "ErrorMessage31": 144,
    "ErrorMessage32": 671,
    "ErrorMessage33": 113,
    "ErrorMessage34": 167,
    "ErrorMessage35": 177,
    "ErrorMessage4": 156,
    "ErrorMessage4_1": 118,
    "ErrorMessage43": 592,
    "ErrorMessage5": 398,
    "ErrorMessage6": 162,
    "ErrorMessage6_1": 123,
    "ErrorMessage7": 306,
    "ErrorMessage8": 183,
    "ErrorMessage9": 189,
    "EventDetails": 369,
    "EventEdit": 380,
    "EventForm": 409,
    "FAQs": 438,
    "Feedback": 441,
    "Feedback_Column1": 630,
    "FileUpload": 451,
    "Footer": 14,
    "Form1_1": 98,
    "Form2": 300,
    "Form2_1": 659,
    "Form3": 392,
    "Form3_1": 587,
    "Form3_2": 666,
    "Form4": 209,
    "Form5": 454,
    "FullDescription_DataCard1": 109,
    "Gallery1": 28,
    "Gallery1_1": 486,
    "Gallery11": 720,
    "Gallery12": 722,
    "Gallery18": 59,
    "Gallery18_1": 319,
    "Gallery2": 446,
    "Gallery2_1": 520,
    "Gallery3": 270,
    "Gallery4": 337,
    "Gallery5": 685,
    "Gallery7": 368,
    "Gallery9": 77,
    "galleryTemplate1": 19,
    "galleryTemplate1_1": 487,
    "galleryTemplate10": 78,
    "galleryTemplate11": 721,
    "galleryTemplate12": 723,
    "galleryTemplate18": 60,
    "galleryTemplate18_1": 320,
    "galleryTemplate2": 447,
    "galleryTemplate2_1": 281,
    "galleryTemplate2_2": 521,
    "galleryTemplate3": 29,
    "galleryTemplate3_1": 284,
    "galleryTemplate4": 338,
    "galleryTemplate5": 271,
    "galleryTemplate6": 686,
    "galleryTemplate7": 369,
    "galPaginated": 18,
    "Group1": 89,
    "Guild Form": 455,
    "Guild_DataCard1": 215,
    "GuildStats": 567,
    "Home": 593,
    "HomeDropDown": 66,
    "HomeImage": 24,
    "HtmlText2": 359,
    "HtmlText3": 439,
    "Icon1": 348,
    "Icon10": 365,
    "Icon10_1": 577,
    "Icon11": 23,
    "Icon12": 349,
    "Icon13": 361,
    "Icon14": 333,
    "Icon15": 290,
    "Icon16": 381,
    "Icon17": 444,
    "Icon18": 239,
    "Icon19": 480,
    "Icon2": 698,
    "Icon20": 76,
    "Icon21": 449,
    "Icon22": 725,
    "Icon23": 451,
    "Icon24": 501,
    "Icon25": 347,
    "Icon26": 24,
    "Icon27": 58,
    "Icon27_1": 318,
    "Icon29": 484,
    "Icon3": 7,
    "Icon3_1": 313,
    "Icon3_2": 405,
    "Icon3_3": 507,
    "Icon3_4": 6,
    "Icon3_5": 8,
    "Icon3_6": 508,
    "Icon3_7": 314,
    "Icon30": 276,
    "Icon31": 278,
    "Icon32": 674,
    "Icon33": 595,
    "Icon4": 555,
    "Icon4_2": 491,
    "Icon5": 56,
    "Icon5_1": 519,
    "Icon5_2": 638,
    "Icon5_3": 316,
    "Icon6": 27,
    "Icon7": 208,
    "Icon7_1": 565,
    "Icon8": 97,
    "Icon9": 91,
    "iconNextMonth1_1": 269,
    "iconPrevMonth1_1": 268,
    "Image_DataCard1": 196,
    "Image_DataCard2": 301,
    "Image_DataCard3": 393,
    "Image1": 704,
    "Image1_1": 719,
    "Image1_DataCard1": 124,
    "Image10": 45,
    "Image10_1": 262,
    "Image10_2": 260,
    "Image10_3": 261,
    "Image10_4": 46,
    "Image11": 716,
    "Image11_1": 712,
    "Image11_2": 713,
    "Image11_3": 714,
    "Image11_4": 568,
    "Image12": 51,
    "Image13": 52,
    "Image14": 92,
    "Image14_1": 93,
    "Image14_2": 94,
    "Image15": 339,
    "Image16": 364,
    "Image17": 352,
    "Image18": 396,
    "Image2": 717,
    "Image2_1": 488,
    "Image20": 127,
    "Image21": 199,
    "Image22": 54,
    "Image23": 357,
    "Image24": 370,
    "Image25": 729,
    "Image25_1": 730,
    "Image25_2": 731,
    "Image26": 5,
    "Image27": 154,
    "Image28": 160,
    "Image29": 181,
    "Image3": 20,
    "Image3_1": 245,
    "Image3_2": 254,
    "Image30": 187,
    "Image31": 193,
    "Image34": 687,
    "Image4": 148,
    "Image4_1": 255,
    "Image5": 700,
    "Image5_1": 253,
    "Image6": 53,
    "Image7": 711,
    "Image7_1": 602,
    "Image8": 302,
    "Image8_1": 515,
    "Image9": 247,
    "Label1": 41,
    "Label1_1": 493,
    "Label10": 647,
    "Label10_1": 516,
    "Label11": 293,
    "Label11_1": 297,
    "Label11_2": 386,
    "Label11_3": 390,
    "Label11_4": 557,
    "Label11_5": 649,
    "Label12": 241,
    "Label12_1": 560,
    "Label12_2": 648,
    "Label13": 240,
    "Label13_1": 530,
    "Label13_2": 658,
    "Label14": 499,
    "Label15": 353,
    "Label16": 355,
    "Label16_1": 569,
    "Label17": 354,
    "Label17_1": 570,
    "Label18": 362,
    "Label18_1": 571,
    "Label19": 250,
    "Label2": 703,
    "Label2_1": 514,
    "Label2_2": 492,
    "Label2_4": 604,
    "Label2_5": 600,
    "Label2_6": 607,
    "Label2_7": 609,
    "Label20": 728,
    "Label21": 363,
    "Label21_1": 572,
    "Label22": 375,
    "Label22_1": 573,
    "Label23": 295,
    "Label24": 376,
    "Label24_1": 574,
    "Label25": 299,
    "Label26": 388,
    "Label26_1": 575,
    "Label27": 248,
    "Label28": 384,
    "Label28_1": 576,
    "Label29": 246,
    "Label3": 709,
    "Label3_1": 496,
    "Label3_4": 601,
    "Label3_5": 605,
    "Label3_6": 610,
    "Label3_7": 606,
    "Label30": 249,
    "Label31": 544,
    "Label32": 578,
    "Label33": 582,
    "Label34": 579,
    "Label35": 580,
    "Label36": 583,
    "Label37": 585,
    "Label38": 584,
    "Label39": 581,
    "Label4": 710,
    "Label4_1": 625,
    "Label4_3": 632,
    "Label40": 273,
    "Label41": 274,
    "Label42": 684,
    "Label43": 26,
    "Label44": 277,
    "Label45": 275,
    "Label46": 677,
    "Label47": 31,
    "Label48": 683,
    "Label49": 36,
    "Label5": 715,
    "Label5_1": 252,
    "Label5_2": 599,
    "Label5_3": 653,
    "Label6": 12,
    "Label6_1": 608,
    "Label6_2": 654,
    "Label6_3": 655,
    "Label6_4": 256,
    "Label6_5": 257,
    "Label6_7": 258,
    "Label7": 500,
    "Label7_1": 641,
    "Label8": 88,
    "Label8_1": 556,
    "Label8_2": 642,
    "Label9": 643,
    "Label9_1": 265,
    "Label9_2": 264,
    "Label9_3": 263,
    "Label9_4": 518,
    "Label9_5": 554,
    "LblAppName1": 85,
    "LblAppName10": 637,
    "LblAppName2": 441,
    "LblAppName3": 289,
    "LblAppName4": 673,
    "LblAppName5": 483,
    "LblAppName6": 346,
    "LblAppName7": 380,
    "LblAppName8": 564,
    "LblAppName9": 594,
    "LblMonthSelected1_1": 267,
    "lblPagination": 35,
    "Legend1": 414,
    "Legend1_1": 538,
    "Legend10": 622,
    "Legend2": 415,
    "Legend4": 424,
    "Legend5_1": 537,
    "Legend6": 423,
    "Legend6_1": 623,
    "Legend8": 432,
    "Legend9": 621,
    "LineChart1": 412,
    "LineChart1_1": 536,
    "LineChart2": 620,
    "Link_DataCard1": 667,
    "Members_Column1": 547,
    "MicrosoftStream2": 44,
    "MonthDayGallery1_1": 283,
    "Name_Column1": 429,
    "Name_DataCard1": 465,
    "NavBar": 26,
    "NavBarGr": 2,
    "NavBarGr_1": 404,
    "NavBarGr_2": 504,
    "NavBarGr_3": 310,
    "NextArrow2": 490,
    "NextArrow20": 62,
    "NextArrow20_1": 322,
    "NextArrow6": 79,
    "No_Column1": 542,
    "PdfViewer1": 495,
    "PieChart3": 421,
    "PieChart4": 619,
    "PieChart5": 431,
    "Points_Column1": 430,
    "Polestar1_DataCard1": 114,
    "Profile": 696,
    "Rectangle1": 374,
    "Rectangle2": 70,
    "Rectangle2_1": 433,
    "Rectangle2_3": 548,
    "Rectangle2_4": 328,
    "Rectangle3": 65,
    "Rectangle4": 87,
    "Rectangle6": 68,
    "Rectangle6_1": 509,
    "Rectangle6_2": 329,
    "Rectangle7": 272,
    "Rectangle8": 718,
    "RectQuickActionBar1": 0,
    "RectQuickActionBar1_2": 238,
    "RectQuickActionBar10": 482,
    "RectQuickActionBar11": 563,
    "RectQuickActionBar12": 593,
    "RectQuickActionBar13": 636,
    "RectQuickActionBar2": 672,
    "RectQuickActionBar3": 440,
    "RectQuickActionBar4": 288,
    "RectQuickActionBar5": 399,
    "RectQuickActionBar6": 308,
    "RectQuickActionBar7": 345,
    "RectQuickActionBar8": 379,
    "RectQuickActionBar9": 502,
    "RichTextEditor1": 561,
    "Separator1": 343,
    "Separator2": 494,
    "Separator22": 64,
    "Separator22_1": 324,
    "Separator4": 32,
    "Separator5": 453,
    "Separator6_1": 528,
    "Separator7": 373,
    "Separator9": 81,
    "shareIt": 740,
    "Short Description_DataCard2": 104,
    "Star1_1": 603,
    "StarVisible1": 100,
    "StarVisible10": 191,
    "StarVisible11": 131,
    "StarVisible12": 136,
    "StarVisible13": 216,
    "StarVisible14": 125,
    "StarVisible15": 197,
    "StarVisible17": 203,
    "StarVisible18": 456,
    "StarVisible18_1": 661,
    "StarVisible19": 211,
    "StarVisible2": 146,
    "StarVisible20": 221,
    "StarVisible22": 226,
    "StarVisible23": 231,
    "StarVisible24": 461,
    "StarVisible25": 466,
    "StarVisible26": 471,
    "StarVisible27": 476,
    "StarVisible29": 169,
    "StarVisible3": 105,
    "StarVisible31": 141,
    "StarVisible32": 670,
    "StarVisible33": 110,
    "StarVisible34": 164,
    "StarVisible35": 174,
    "StarVisible4": 152,
    "StarVisible4_1": 115,
    "StarVisible43": 590,
    "StarVisible5": 394,
    "StarVisible6": 158,
    "StarVisible6_1": 120,
    "StarVisible7": 304,
    "StarVisible8": 179,
    "StarVisible9": 185,
    "Subcircle1_1": 286,
    "Subtitle1": 22,
    "Subtitle2": 342,
    "Subtitle20": 63,
    "Subtitle20_1": 323,
    "Subtitle6": 450,
    "Subtitle7": 689,
    "Subtitle7_1": 523,
    "Subtitle8": 372,
    "TextInput1": 697,
    "TextInput1_1": 657,
    "TextInput10": 39,
    "TextInput11": 49,
    "TextInput2": 701,
    "TextInput3": 699,
    "TextInput3_1": 558,
    "TextInput3_2": 646,
    "TextInput4": 48,
    "TextInput4_1": 652,
    "TextInput5": 366,
    "TextInput6": 331,
    "TextInput7": 42,
    "TextInput9": 15,
    "TextInput9_1": 16,
    "Timer1": 96,
    "title": 294,
    "title_1": 387,
    "Title_Column1": 546,
    "Title_Column2_1": 628,
    "Title_DataCard1": 99,
    "Title_DataCard2": 455,
    "Title_DataCard4": 210,
    "Title1": 21,
    "Title1_1": 535,
    "Title1_2": 539,
    "Title10": 427,
    "Title10_1": 616,
    "Title11": 448,
    "Title11_1": 615,
    "Title13": 371,
    "Title14": 688,
    "Title15": 30,
    "Title18": 80,
    "Title2": 409,
    "Title2_1": 282,
    "Title2_2": 489,
    "Title26": 61,
    "Title26_1": 321,
    "Title3": 410,
    "Title3_1": 285,
    "Title4": 340,
    "Title5": 418,
    "Title5_2": 533,
    "Title6": 692,
    "Title7": 617,
    "Title8": 417,
    "Title8_1": 522,
    "Title9": 694,
    "Top Communities_1": 532,
    "Torch Bearers1_DataCard1": 130,
    "Torch Bearers2_DataCard1": 135,
    "Torch Bearers3_DataCard1": 140,
    "TorchImage1_DataCard1": 145,
    "TorchImage2_DataCard1": 151,
    "TorchImage3_DataCard1": 157,
    "Trend Setters1_DataCard1": 163,
    "Trend Setters2_DataCard1": 168,
    "Trend Setters3_DataCard2": 173,
    "TrendImage1_DataCard1": 178,
    "TrendImage2_DataCard1": 184,
    "TrendImage3_DataCard1": 190,
    "UpcomingGuild": 37,
    "UpcomingGuild_1": 38,
    "UserName": 57,
    "UserName_1": 317,
    "UserName_Column1": 541,
    "WeekdayGallery1_1": 280,
    "WhitePapers": 742
  },
  "ResourcesJsonIndices": {
    "Image-237704527_10159698642244138_333429640887957773_n": 35,
    "Image-Anand V": 3,
    "Image-baishali roy": 4,
    "Image-facebook-square": 5,
    "Image-guild_product": 6,
    "Image-guild_supply": 7,
    "Image-guild_wealth": 8,
    "Image-Harshal Jawale": 9,
    "Image-Image": 12,
    "Image-Image (1)": 10,
    "Image-Image (2)": 11,
    "Image-Image1_2": 13,
    "Image-Image2_2": 14,
    "Image-jayakanth abhimanyu": 15,
    "Image-linkedin": 16,
    "Image-logo": 17,
    "Image-MicrosoftTeams-image (1)": 18,
    "Image-MicrosoftTeams-image (2)": 19,
    "Image-MicrosoftTeams-image (3)": 20,
    "Image-poojatest": 21,
    "Image-poojatest1": 22,
    "Image-priya": 23,
    "Image-priyatest": 24,
    "Image-priyatest1": 25,
    "Image-Quotes1": 26,
    "Image-Quotes2": 27,
    "Image-Rohan Kudav": 28,
    "Image-SampleImage": 0,
    "Image-sanjeev korupolu": 29,
    "Image-soundarya cholkar": 30,
    "Image-square-facebook": 31,
    "Image-square-twitter": 32,
    "Image-testomonial": 33,
    "Image-youtube": 34,
    "Pdf-SamplePdf": 1,
    "Video-SampleVideo": 2
  },
  "RuleScreenIdWithoutScreen": {},
  "TemplateVersions": {},
  "VolatileProperties": {
    "AnalysisLoadTime": 4.4177904,
    "ControlCount": {
      "0927d2b0e1b146c68bb9d9479edc1044": 1,
      "62dc4f1561b4448e901618e4647b41b4": 5,
      "923589e162334ba3ac42a49447cb3358": 2,
      "abc5859afff742348a300a44f7269761": 1,
      "addMedia": 10,
      "arrow": 2,
      "attachments": 6,
      "barChart": 6,
      "button": 65,
      "circle": 2,
      "dataCard": 36,
      "dataTable": 6,
      "dataTableColumn": 13,
      "datepicker": 4,
      "dropdown": 11,
      "f210c8996a1c4890ba04d40592a3d7d0": 2,
      "f519ced9060241e4947d9bc36dcc7f62": 2,
      "fluidGrid": 13,
      "form": 8,
      "gallery": 16,
      "galleryTemplate": 16,
      "group": 21,
      "groupContainer": 4,
      "htmlViewer": 2,
      "icon": 52,
      "image": 51,
      "label": 251,
      "legend": 10,
      "lineChart": 3,
      "microsoftStreamPlayback": 1,
      "pdfViewer": 1,
      "pieChart": 3,
      "rectangle": 35,
      "richTextEditor": 3,
      "screen": 23,
      "star": 1,
      "text": 37,
      "timer": 1,
      "typedDataCard": 35
    },
    "DeserializationLoadTime": 9.4489339,
    "ErrorCount": 18
  },
  "WasLocalDatabaseReferencesEmpty": false
}