{
  "ComponentIndexes": {
    "About": 22,
    "Component1": 23,
    "Footer": 24,
    "HomeImage": 25,
    "NavBar": 26,
    "UpcomingGuild": 27
  },
  "ControlUniqueGuids": {},
  "ControlUniqueIds": {
    "About": 8,
    "ActivityDetails": 600,
    "AddActivity": 693,
    "AddPicture1": 541,
    "AddPicture10": 586,
    "AddPicture2": 292,
    "AddPicture3": 691,
    "AddPicture5": 547,
    "AddPicture5_1": 520,
    "AddPicture6": 592,
    "AddPicture7": 553,
    "AddPicture8": 574,
    "AddPicture9": 580,
    "Admin": 389,
    "allBlogs": 44,
    "AllBlogs": 730,
    "App": 1,
    "Attachments_DataCard1": 594,
    "Attachments_DataCard2": 464,
    "Attachments_DataCard2_1": 626,
    "Attachments_DataCard2_2": 718,
    "Attachments_DataCard4": 348,
    "Body1_1": 413,
    "Body2": 308,
    "btnNext": 122,
    "btnPrevious": 121,
    "Button1": 173,
    "Button1_1": 314,
    "Button1_2": 154,
    "Button1_3": 177,
    "Button1_4": 169,
    "Button1_5": 158,
    "Button10": 679,
    "Button11": 67,
    "Button12": 30,
    "Button14": 470,
    "Button16": 33,
    "Button16_1": 32,
    "Button17": 152,
    "Button17_1": 666,
    "Button17_3": 435,
    "Button17_4": 62,
    "Button18": 160,
    "Button18_1": 168,
    "Button18_12": 439,
    "Button18_13": 438,
    "Button18_14": 437,
    "Button18_15": 436,
    "Button18_16": 79,
    "Button18_17": 71,
    "Button18_18": 70,
    "Button18_19": 65,
    "Button18_2": 170,
    "Button18_3": 172,
    "Button18_4": 670,
    "Button18_5": 669,
    "Button18_6": 668,
    "Button18_7": 667,
    "Button2": 76,
    "Button2_3": 7,
    "Button2_4": 487,
    "Button2_5": 5,
    "Button2_6": 6,
    "Button20_1": 86,
    "Button20_10": 635,
    "Button20_11": 636,
    "Button20_12": 634,
    "Button20_3": 393,
    "Button20_5": 85,
    "Button20_6": 392,
    "Button20_7": 47,
    "Button20_8": 48,
    "Button3": 14,
    "Button3_1": 411,
    "Button4": 353,
    "Button4_1": 410,
    "Button5": 157,
    "Button5_1": 483,
    "Button5_2": 189,
    "Button5_3": 599,
    "Button5_4": 397,
    "Button5_5": 63,
    "Button6": 296,
    "Button6_1": 624,
    "Button7": 387,
    "Button8": 388,
    "Button8_1": 412,
    "Button8_2": 723,
    "Button9": 301,
    "Canvas1": 91,
    "Canvas1_1": 235,
    "Canvas10": 190,
    "Canvas11": 697,
    "Canvas2": 272,
    "Canvas3": 733,
    "Canvas4": 280,
    "Canvas5": 638,
    "Canvas6": 398,
    "Canvas7": 360,
    "Canvas8": 676,
    "Canvas9": 604,
    "Circle1_1": 120,
    "ColumnChart1": 643,
    "ColumnChart2": 652,
    "ColumnChart3": 208,
    "Communities_Column1_1": 227,
    "Community": 229,
    "CommunityRole_Column1_1": 228,
    "Component1": 3,
    "Component1_1": 84,
    "Component1_2": 46,
    "Component1_3": 633,
    "Component1_4": 391,
    "Component2_1": 93,
    "Component3_1": 96,
    "CompositeColumnChart1": 647,
    "CompositeColumnChart2": 656,
    "CompositeColumnChart2_1": 428,
    "CompositeColumnChart4": 216,
    "CompositeLineChart1": 646,
    "CompositeLineChart1_1": 427,
    "CompositeLineChart2": 214,
    "CompositePieChart3": 655,
    "CompositePieChart4": 215,
    "CompositePieChart5": 664,
    "Container1": 35,
    "Container2": 51,
    "Container3": 161,
    "Container5": 142,
    "content": 287,
    "content_1": 685,
    "createBlog": 276,
    "Dashboard": 631,
    "DataCard1": 130,
    "DataCard10": 281,
    "DataCard11": 639,
    "DataCard12": 648,
    "DataCard13": 95,
    "DataCard14": 368,
    "DataCard15": 677,
    "DataCard16": 657,
    "DataCard17": 370,
    "DataCard18": 734,
    "DataCard19": 399,
    "DataCard2": 99,
    "DataCard2_1": 236,
    "DataCard20": 377,
    "DataCard21": 366,
    "DataCard22": 415,
    "DataCard23": 244,
    "DataCard24": 605,
    "DataCard25": 252,
    "DataCard27": 191,
    "DataCard28": 698,
    "DataCard29": 204,
    "DataCard3": 127,
    "DataCard30": 217,
    "DataCard31": 224,
    "DataCard32": 429,
    "DataCard33": 735,
    "DataCard4": 134,
    "DataCard5": 137,
    "DataCard6": 124,
    "DataCard7": 273,
    "DataCard8": 92,
    "DataCard9": 361,
    "DataCardKey1": 493,
    "DataCardKey10": 584,
    "DataCardKey11": 524,
    "DataCardKey12": 529,
    "DataCardKey14": 518,
    "DataCardKey15": 590,
    "DataCardKey17": 596,
    "DataCardKey18": 446,
    "DataCardKey18_1": 720,
    "DataCardKey19": 330,
    "DataCardKey2": 539,
    "DataCardKey20": 335,
    "DataCardKey21": 340,
    "DataCardKey22": 345,
    "DataCardKey23": 350,
    "DataCardKey24": 451,
    "DataCardKey25": 456,
    "DataCardKey26": 461,
    "DataCardKey27": 466,
    "DataCardKey29": 562,
    "DataCardKey3": 498,
    "DataCardKey31": 534,
    "DataCardKey32": 727,
    "DataCardKey33": 503,
    "DataCardKey34": 557,
    "DataCardKey35": 567,
    "DataCardKey4": 545,
    "DataCardKey4_1": 508,
    "DataCardKey43": 629,
    "DataCardKey5": 689,
    "DataCardKey6": 551,
    "DataCardKey6_1": 513,
    "DataCardKey7": 294,
    "DataCardKey8": 572,
    "DataCardKey9": 578,
    "DataCardValue1": 494,
    "DataCardValue11": 597,
    "DataCardValue12": 447,
    "DataCardValue13": 452,
    "DataCardValue14": 457,
    "DataCardValue15": 462,
    "DataCardValue16": 467,
    "DataCardValue17": 331,
    "DataCardValue17_1": 721,
    "DataCardValue18": 336,
    "DataCardValue19": 341,
    "DataCardValue20": 346,
    "DataCardValue21": 351,
    "DataCardValue23": 563,
    "DataCardValue25": 535,
    "DataCardValue26": 504,
    "DataCardValue27": 558,
    "DataCardValue28": 568,
    "DataCardValue3_1": 499,
    "DataCardValue31": 726,
    "DataCardValue4_1": 509,
    "DataCardValue42": 627,
    "DataCardValue5_1": 514,
    "DataCardValue8": 525,
    "DataCardValue8_1": 486,
    "DataCardValue9": 530,
    "DataTable1": 659,
    "DataTable1_1": 226,
    "DataTable2": 424,
    "DataTable3": 431,
    "DataTable3_1": 220,
    "Date_DataCard1": 459,
    "Date_DataCard2": 343,
    "DateofEvent_Column1_1": 222,
    "DatePicker1": 480,
    "DatePicker1_1": 708,
    "ddPageSize": 107,
    "Description_DataCard1": 449,
    "Description_DataCard3": 333,
    "Designation1_DataCard1": 511,
    "detailBlog": 354,
    "detailBlog2": 274,
    "Dropdown1": 69,
    "Dropdown1_1": 219,
    "Dropdown2": 285,
    "Dropdown2_1": 683,
    "Dropdown2_2": 702,
    "Dropdown3": 703,
    "Dropdown4": 709,
    "Dropdown5": 714,
    "Dropdown6": 403,
    "DtopDownDash": 184,
    "DtopDownDash_1": 441,
    "DtopDownDash_2": 81,
    "editBlog": 672,
    "ErrorMessage1": 495,
    "ErrorMessage10": 587,
    "ErrorMessage11": 526,
    "ErrorMessage12": 531,
    "ErrorMessage14": 521,
    "ErrorMessage15": 593,
    "ErrorMessage17": 598,
    "ErrorMessage18": 448,
    "ErrorMessage18_1": 722,
    "ErrorMessage19": 332,
    "ErrorMessage2": 542,
    "ErrorMessage20": 337,
    "ErrorMessage21": 342,
    "ErrorMessage22": 347,
    "ErrorMessage23": 352,
    "ErrorMessage24": 453,
    "ErrorMessage25": 458,
    "ErrorMessage26": 463,
    "ErrorMessage27": 468,
    "ErrorMessage29": 564,
    "ErrorMessage3": 500,
    "ErrorMessage31": 536,
    "ErrorMessage32": 729,
    "ErrorMessage33": 505,
    "ErrorMessage34": 559,
    "ErrorMessage35": 569,
    "ErrorMessage4": 548,
    "ErrorMessage4_1": 510,
    "ErrorMessage43": 630,
    "ErrorMessage5": 692,
    "ErrorMessage6": 554,
    "ErrorMessage6_1": 515,
    "ErrorMessage7": 295,
    "ErrorMessage8": 575,
    "ErrorMessage9": 581,
    "EventDetails": 299,
    "EventEdit": 442,
    "EventForm": 325,
    "FAQs": 471,
    "Feedback": 474,
    "Feedback_Column1": 223,
    "FileUpload": 484,
    "Footer": 34,
    "Form1_1": 490,
    "Form2": 289,
    "Form2_1": 717,
    "Form3": 686,
    "Form3_1": 625,
    "Form3_2": 724,
    "Form4": 327,
    "Form5": 443,
    "FullDescription_DataCard1": 501,
    "Gallery1_1": 315,
    "Gallery11": 26,
    "Gallery12": 28,
    "Gallery18": 146,
    "Gallery18_1": 55,
    "Gallery2": 302,
    "Gallery2_1": 406,
    "Gallery3": 746,
    "Gallery4": 72,
    "Gallery7": 378,
    "Gallery9": 163,
    "galleryTemplate1": 101,
    "galleryTemplate1_1": 316,
    "galleryTemplate10": 164,
    "galleryTemplate11": 27,
    "galleryTemplate12": 29,
    "galleryTemplate18": 147,
    "galleryTemplate18_1": 56,
    "galleryTemplate2": 303,
    "galleryTemplate2_1": 114,
    "galleryTemplate2_2": 407,
    "galleryTemplate3_1": 117,
    "galleryTemplate4": 73,
    "galleryTemplate5": 747,
    "galleryTemplate7": 379,
    "galPaginated": 100,
    "Group1": 181,
    "Guild Form": 488,
    "Home": 82,
    "HomeDropDown": 183,
    "HomeImage": 21,
    "HtmlText2": 369,
    "HtmlText3": 275,
    "Icon1": 358,
    "Icon10": 375,
    "Icon10_1": 615,
    "Icon11": 105,
    "Icon12": 359,
    "Icon13": 371,
    "Icon14": 68,
    "Icon15": 279,
    "Icon16": 675,
    "Icon17": 300,
    "Icon18": 232,
    "Icon19": 469,
    "Icon2": 10,
    "Icon2_1": 313,
    "Icon20": 162,
    "Icon21": 305,
    "Icon22": 31,
    "Icon23": 307,
    "Icon24": 298,
    "Icon25": 357,
    "Icon26": 106,
    "Icon27": 145,
    "Icon27_1": 54,
    "Icon28": 188,
    "Icon3": 89,
    "Icon3_1": 49,
    "Icon3_2": 637,
    "Icon3_3": 394,
    "Icon3_4": 88,
    "Icon3_5": 90,
    "Icon3_6": 395,
    "Icon3_7": 50,
    "Icon30": 761,
    "Icon4": 476,
    "Icon4_2": 320,
    "Icon5": 143,
    "Icon5_1": 405,
    "Icon5_2": 696,
    "Icon5_3": 52,
    "Icon6": 109,
    "Icon7": 326,
    "Icon7_1": 603,
    "Icon8": 489,
    "Icon9": 176,
    "iconNextMonth1_1": 112,
    "iconPrevMonth1_1": 111,
    "Image_DataCard1": 588,
    "Image_DataCard2": 290,
    "Image_DataCard3": 687,
    "Image1": 4,
    "Image1_1": 25,
    "Image1_DataCard1": 516,
    "Image10": 132,
    "Image10_1": 255,
    "Image10_2": 253,
    "Image10_3": 254,
    "Image10_4": 133,
    "Image11": 43,
    "Image11_1": 39,
    "Image11_2": 40,
    "Image11_3": 41,
    "Image11_4": 606,
    "Image12": 138,
    "Image13": 139,
    "Image14": 178,
    "Image14_1": 179,
    "Image14_2": 180,
    "Image15": 74,
    "Image16": 374,
    "Image17": 362,
    "Image18": 690,
    "Image2": 22,
    "Image2_1": 317,
    "Image20": 519,
    "Image21": 591,
    "Image22": 141,
    "Image23": 367,
    "Image24": 380,
    "Image25": 18,
    "Image25_1": 19,
    "Image25_2": 20,
    "Image26": 87,
    "Image27": 546,
    "Image28": 552,
    "Image29": 573,
    "Image3": 102,
    "Image3_1": 237,
    "Image3_2": 247,
    "Image30": 579,
    "Image31": 585,
    "Image4": 540,
    "Image4_1": 248,
    "Image5": 12,
    "Image5_1": 246,
    "Image6": 140,
    "Image7": 38,
    "Image7_1": 195,
    "Image8": 291,
    "Image8_1": 401,
    "Image9": 239,
    "Label1": 128,
    "Label1_1": 322,
    "Label10": 705,
    "Label10_1": 402,
    "Label11": 282,
    "Label11_1": 286,
    "Label11_2": 680,
    "Label11_3": 684,
    "Label11_4": 478,
    "Label11_5": 707,
    "Label12": 234,
    "Label12_1": 481,
    "Label12_2": 706,
    "Label13": 233,
    "Label13_1": 416,
    "Label13_2": 716,
    "Label14": 472,
    "Label15": 363,
    "Label16": 365,
    "Label16_1": 607,
    "Label17": 364,
    "Label17_1": 608,
    "Label18": 372,
    "Label18_1": 609,
    "Label19": 243,
    "Label2": 15,
    "Label2_1": 400,
    "Label2_2": 321,
    "Label2_4": 197,
    "Label2_5": 193,
    "Label2_6": 200,
    "Label2_7": 202,
    "Label20": 17,
    "Label21": 373,
    "Label21_1": 610,
    "Label22": 385,
    "Label22_1": 611,
    "Label23": 284,
    "Label24": 386,
    "Label24_1": 612,
    "Label25": 288,
    "Label26": 682,
    "Label26_1": 613,
    "Label27": 241,
    "Label28": 678,
    "Label28_1": 614,
    "Label29": 238,
    "Label29_1": 240,
    "Label3": 36,
    "Label3_1": 485,
    "Label3_4": 194,
    "Label3_5": 198,
    "Label3_6": 203,
    "Label3_7": 199,
    "Label30": 242,
    "Label31": 430,
    "Label32": 616,
    "Label33": 620,
    "Label34": 617,
    "Label35": 618,
    "Label36": 621,
    "Label37": 623,
    "Label38": 622,
    "Label39": 619,
    "Label4": 37,
    "Label4_1": 218,
    "Label4_3": 225,
    "Label40": 755,
    "Label41": 756,
    "Label43": 108,
    "Label44": 758,
    "Label45": 759,
    "Label5": 42,
    "Label5_1": 245,
    "Label5_2": 192,
    "Label5_3": 711,
    "Label6": 94,
    "Label6_1": 201,
    "Label6_2": 712,
    "Label6_3": 713,
    "Label6_4": 249,
    "Label6_5": 250,
    "Label6_7": 251,
    "Label7": 473,
    "Label7_1": 699,
    "Label8": 175,
    "Label8_1": 477,
    "Label8_2": 700,
    "Label9": 701,
    "Label9_1": 258,
    "Label9_2": 257,
    "Label9_3": 256,
    "Label9_4": 404,
    "Label9_5": 475,
    "LblAppName1": 171,
    "LblAppName10": 695,
    "LblAppName2": 732,
    "LblAppName3": 278,
    "LblAppName5": 312,
    "LblAppName6": 356,
    "LblAppName7": 674,
    "LblAppName8": 602,
    "LblAppName9": 187,
    "LblMonthSelected1_1": 110,
    "lblPagination": 123,
    "Legend1": 644,
    "Legend1_1": 422,
    "Legend10": 212,
    "Legend2": 645,
    "Legend4": 654,
    "Legend5_1": 421,
    "Legend6": 653,
    "Legend6_1": 213,
    "Legend8": 663,
    "Legend9": 211,
    "LineChart1": 642,
    "LineChart1_1": 420,
    "LineChart2": 210,
    "Link_DataCard1": 725,
    "Members_Column1": 433,
    "MicrosoftStream2": 131,
    "MonthDayGallery1_1": 116,
    "Name_Column1": 660,
    "Name_DataCard1": 454,
    "Name_DataCard2": 338,
    "NavBar": 23,
    "NavBarGr": 182,
    "NavBarGr_1": 671,
    "NavBarGr_2": 440,
    "NavBarGr_3": 80,
    "NextArrow2": 319,
    "NextArrow20": 149,
    "NextArrow20_1": 58,
    "NextArrow6": 165,
    "No_Column1": 426,
    "PdfViewer1": 324,
    "PieChart3": 651,
    "PieChart4": 209,
    "PieChart5": 662,
    "Points_Column1": 661,
    "Polestar1_DataCard1": 506,
    "Profile": 185,
    "Rectangle1": 384,
    "Rectangle2": 155,
    "Rectangle2_1": 665,
    "Rectangle2_3": 434,
    "Rectangle2_4": 64,
    "Rectangle3": 153,
    "Rectangle4": 174,
    "Rectangle6": 156,
    "Rectangle6_1": 396,
    "Rectangle6_2": 61,
    "Rectangle8": 24,
    "RectQuickActionBar1": 83,
    "RectQuickActionBar1_2": 231,
    "RectQuickActionBar10": 311,
    "RectQuickActionBar11": 601,
    "RectQuickActionBar12": 186,
    "RectQuickActionBar13": 694,
    "RectQuickActionBar2": 230,
    "RectQuickActionBar3": 731,
    "RectQuickActionBar4": 277,
    "RectQuickActionBar5": 632,
    "RectQuickActionBar6": 45,
    "RectQuickActionBar7": 355,
    "RectQuickActionBar8": 673,
    "RectQuickActionBar9": 390,
    "RichTextEditor1": 482,
    "Separator1": 78,
    "Separator2": 323,
    "Separator22": 151,
    "Separator22_1": 60,
    "Separator5": 309,
    "Separator6_1": 414,
    "Separator7": 383,
    "Separator9": 167,
    "shareIt": 297,
    "Short Description_DataCard2": 496,
    "Star1_1": 196,
    "StarVisible1": 492,
    "StarVisible10": 583,
    "StarVisible11": 523,
    "StarVisible12": 528,
    "StarVisible14": 517,
    "StarVisible15": 589,
    "StarVisible17": 595,
    "StarVisible18": 445,
    "StarVisible18_1": 719,
    "StarVisible19": 329,
    "StarVisible2": 538,
    "StarVisible20": 334,
    "StarVisible21": 339,
    "StarVisible22": 344,
    "StarVisible23": 349,
    "StarVisible24": 450,
    "StarVisible25": 455,
    "StarVisible26": 460,
    "StarVisible27": 465,
    "StarVisible29": 561,
    "StarVisible3": 497,
    "StarVisible31": 533,
    "StarVisible32": 728,
    "StarVisible33": 502,
    "StarVisible34": 556,
    "StarVisible35": 566,
    "StarVisible4": 544,
    "StarVisible4_1": 507,
    "StarVisible43": 628,
    "StarVisible5": 688,
    "StarVisible6": 550,
    "StarVisible6_1": 512,
    "StarVisible7": 293,
    "StarVisible8": 571,
    "StarVisible9": 577,
    "Subcircle1_1": 119,
    "Subtitle1": 104,
    "Subtitle2": 77,
    "Subtitle20": 150,
    "Subtitle20_1": 59,
    "Subtitle6": 306,
    "Subtitle7_1": 409,
    "Subtitle8": 382,
    "TextInput1": 9,
    "TextInput1_1": 715,
    "TextInput10": 126,
    "TextInput11": 136,
    "TextInput2": 13,
    "TextInput3": 11,
    "TextInput3_1": 479,
    "TextInput3_2": 704,
    "TextInput4": 135,
    "TextInput4_1": 710,
    "TextInput5": 376,
    "TextInput6": 66,
    "TextInput7": 129,
    "TextInput9": 97,
    "TextInput9_1": 98,
    "Timer1": 159,
    "title": 283,
    "title_1": 681,
    "Title_Column1": 432,
    "Title_Column2_1": 221,
    "Title_DataCard1": 491,
    "Title_DataCard2": 444,
    "Title_DataCard4": 328,
    "Title1": 103,
    "Title1_1": 419,
    "Title1_2": 423,
    "Title10": 658,
    "Title10_1": 206,
    "Title11": 304,
    "Title11_1": 205,
    "Title13": 381,
    "Title18": 166,
    "Title2": 640,
    "Title2_1": 115,
    "Title2_2": 318,
    "Title26": 148,
    "Title26_1": 57,
    "Title3": 641,
    "Title3_1": 118,
    "Title4": 75,
    "Title5": 650,
    "Title5_2": 418,
    "Title7": 207,
    "Title8": 649,
    "Title8_1": 408,
    "Top Communities_1": 417,
    "Torch Bearers1_DataCard1": 522,
    "Torch Bearers2_DataCard1": 527,
    "Torch Bearers3_DataCard1": 532,
    "TorchImage1_DataCard1": 537,
    "TorchImage2_DataCard1": 543,
    "TorchImage3_DataCard1": 549,
    "Trend Setters1_DataCard1": 555,
    "Trend Setters2_DataCard1": 560,
    "Trend Setters3_DataCard2": 565,
    "TrendImage1_DataCard1": 570,
    "TrendImage2_DataCard1": 576,
    "TrendImage3_DataCard1": 582,
    "UpcomingGuild": 16,
    "UpcomingGuild_1": 125,
    "UserName": 144,
    "UserName_1": 53,
    "UserName_Column1": 425,
    "WeekdayGallery1_1": 113,
    "WhitePapers": 310
  },
  "FunctionParamsInvariantScripts": {},
  "FunctionParamsInvariantScriptsOnInstances": {},
  "HeaderLastSavedDateTimeUTC": "12/29/2022 05:32:56",
  "IsLegacyComponentAllowGlobalScopeCase": false,
  "LocalConnectionIDReferences": {
    "55bd11ce-1540-4e1d-8336-43032c5b7e78": "\"/providers/microsoft.powerapps/apis/shared_office365/connections/71f89eebad4047b788deb408d37e182e\"",
    "59bc595d-2c49-4295-b900-697078d27880": "\"/providers/microsoft.powerapps/apis/shared_sharepointonline/connections/shared-sharepointonl-68d94cf9-e6c6-4d43-a62c-96a9ccf9fbd9\"",
    "6cba9de9-2faa-4c8d-b993-358233bbe43e": "\"/providers/microsoft.powerapps/apis/shared_office365users/connections/7ee672b2d966457b89e153b5046320e6\"",
    "992a5415-928d-42ba-b621-3696bdd29ded": "\"/providers/microsoft.powerapps/apis/shared_logicflows/connections/5c42986fc83b4110af7c85ac292220ed\"",
    "9c8341d9-ee49-4114-9936-0c390c4fdcbe": "\"/providers/microsoft.powerapps/apis/shared_logicflows/connections/7403e9f5bf5148bb86f628ee66298a88\"",
    "e55f7f25-74ca-48aa-bbfc-87ca82df5358": "\"/providers/microsoft.powerapps/apis/shared_sharepointonline/connections/shared-sharepointonl-68d94cf9-e6c6-4d43-a62c-96a9ccf9fbd9\""
  },
  "LocalDatabaseReferencesAsEmpty": false,
  "LocalResourceFileNames": {
    "Anand V": "0001.jpg",
    "baishali roy": "0002.jpg",
    "facebook-square": "0003.svg",
    "guild_product": "0004.jpg",
    "guild_supply": "0005.jpg",
    "guild_wealth": "0006.jpg",
    "Harshal Jawale": "0007.jpg",
    "Image": "0010.jpeg",
    "Image (1)": "0008.jpeg",
    "Image (2)": "0009.jpeg",
    "Image1_2": "0011.jpeg",
    "Image2_2": "0012.jpeg",
    "jayakanth abhimanyu": "0013.jpg",
    "linkedin": "0014.svg",
    "logo": "0015.jpg",
    "MicrosoftTeams-image (1)": "0016.png",
    "MicrosoftTeams-image (2)": "0017.png",
    "MicrosoftTeams-image (3)": "0018.png",
    "poojatest": "0019.PNG",
    "poojatest1": "0020.png",
    "priya": "0021.PNG",
    "priyatest": "0022.PNG",
    "priyatest1": "0023.png",
    "Quotes1": "0024.png",
    "Quotes2": "0025.png",
    "Rohan Kudav": "0026.jpg",
    "sanjeev korupolu": "0027.jpg",
    "soundarya cholkar": "0028.jpg",
    "square-facebook": "0029.svg",
    "square-twitter": "0030.svg",
    "testomonial": "0031.PNG",
    "youtube": "0032.svg"
  },
  "LocalResourceRootPaths": {
    "Anand V": "https://docserverpwaprodcin.blob.core.windows.net/8840118c-b0eb-466f-95b4-3aaa48152688-1/resource/Assets0Images00001.jpg?sv=2017-04-17&sr=b&sig=07FSOOV%2F%2Bpr%2FXesITbAQyXkhqnnpyHsArYKC46pZ%2FU4%3D&spr=https&se=2022-12-30T04%3A37%3A15Z&sp=r",
    "baishali roy": "https://docserverpwaprodcin.blob.core.windows.net/8840118c-b0eb-466f-95b4-3aaa48152688-1/resource/Assets0Images00002.jpg?sv=2017-04-17&sr=b&sig=2K7BeFerkd%2FMMBJ%2FYvi1XRNCYSVrGogUy1NJFAusTEs%3D&spr=https&se=2022-12-30T04%3A37%3A15Z&sp=r",
    "facebook-square": "https://docserverpwaprodcin.blob.core.windows.net/8840118c-b0eb-466f-95b4-3aaa48152688-1/resource/Assets0Images00003.svg?sv=2017-04-17&sr=b&sig=PQ6rQksJUm49%2BGXFvf9pH5j4TAJutx55wtbxUHYIDLA%3D&spr=https&se=2022-12-30T04%3A37%3A15Z&sp=r",
    "guild_product": "https://docserverpwaprodcin.blob.core.windows.net/8840118c-b0eb-466f-95b4-3aaa48152688-1/resource/Assets0Images00004.jpg?sv=2017-04-17&sr=b&sig=DaKpaCsKkfWS2ZlxKJkk9gEx8HxO%2FddBfBQSbpTIR5E%3D&spr=https&se=2022-12-30T04%3A37%3A15Z&sp=r",
    "guild_supply": "https://docserverpwaprodcin.blob.core.windows.net/8840118c-b0eb-466f-95b4-3aaa48152688-1/resource/Assets0Images00005.jpg?sv=2017-04-17&sr=b&sig=knLFGZcOn%2FQAgEgOaeEusoobQaFuEefRsAIwKGyR9CI%3D&spr=https&se=2022-12-30T04%3A37%3A15Z&sp=r",
    "guild_wealth": "https://docserverpwaprodcin.blob.core.windows.net/8840118c-b0eb-466f-95b4-3aaa48152688-1/resource/Assets0Images00006.jpg?sv=2017-04-17&sr=b&sig=x%2BJyiixcz2Ro5H9PciFzIoFI%2F7e3%2FHzxlNM7tMGmBEo%3D&spr=https&se=2022-12-30T04%3A37%3A15Z&sp=r",
    "Harshal Jawale": "https://docserverpwaprodcin.blob.core.windows.net/8840118c-b0eb-466f-95b4-3aaa48152688-1/resource/Assets0Images00007.jpg?sv=2017-04-17&sr=b&sig=77EnsK3sK3xONF%2FVQSVSxDcHd62uCXAAPRFUbw4DwOU%3D&spr=https&se=2022-12-30T04%3A37%3A15Z&sp=r",
    "Image": "https://docserverpwaprodcin.blob.core.windows.net/8840118c-b0eb-466f-95b4-3aaa48152688-1/resource/Assets0Images00010.jpeg?sv=2017-04-17&sr=b&sig=x3rMXzr5fGP0U%2B5hfJ6PdIQx4lMBBd8ZaUHb0%2ByxhGo%3D&spr=https&se=2022-12-30T04%3A37%3A15Z&sp=r",
    "Image (1)": "https://docserverpwaprodcin.blob.core.windows.net/8840118c-b0eb-466f-95b4-3aaa48152688-1/resource/Assets0Images00008.jpeg?sv=2017-04-17&sr=b&sig=kI0lVi8d3ZGmcXdp2FeS1nBHRukdNJDtPGpRRb66jho%3D&spr=https&se=2022-12-30T04%3A37%3A15Z&sp=r",
    "Image (2)": "https://docserverpwaprodcin.blob.core.windows.net/8840118c-b0eb-466f-95b4-3aaa48152688-1/resource/Assets0Images00009.jpeg?sv=2017-04-17&sr=b&sig=lPlWwZN%2FDUYh8JK0oC0MeidDxfa76CVqHoj61YPfBwI%3D&spr=https&se=2022-12-30T04%3A37%3A15Z&sp=r",
    "Image1_2": "https://docserverpwaprodcin.blob.core.windows.net/8840118c-b0eb-466f-95b4-3aaa48152688-1/resource/Assets0Images00011.jpeg?sv=2017-04-17&sr=b&sig=7PBEOQIL3KxkphuYNahA9BfFJ7wQhsAnQjSOeL8y5O8%3D&spr=https&se=2022-12-30T04%3A37%3A15Z&sp=r",
    "Image2_2": "https://docserverpwaprodcin.blob.core.windows.net/8840118c-b0eb-466f-95b4-3aaa48152688-1/resource/Assets0Images00012.jpeg?sv=2017-04-17&sr=b&sig=WlwJaMzcE3AtygbjkQ0R%2FCbihh0frrzH1XBSQ4bKmvA%3D&spr=https&se=2022-12-30T04%3A37%3A15Z&sp=r",
    "jayakanth abhimanyu": "https://docserverpwaprodcin.blob.core.windows.net/8840118c-b0eb-466f-95b4-3aaa48152688-1/resource/Assets0Images00013.jpg?sv=2017-04-17&sr=b&sig=11QymYrem%2FxZQEFiHI8Dy%2BjKSizDnoaeFIC6%2F63dSmM%3D&spr=https&se=2022-12-30T04%3A37%3A15Z&sp=r",
    "linkedin": "https://docserverpwaprodcin.blob.core.windows.net/8840118c-b0eb-466f-95b4-3aaa48152688-1/resource/Assets0Images00014.svg?sv=2017-04-17&sr=b&sig=bNYAF0HK%2Fco2aZZh5nbORTiwA5%2FoRCdt5U8MjjhIKpk%3D&spr=https&se=2022-12-30T04%3A37%3A15Z&sp=r",
    "logo": "https://docserverpwaprodcin.blob.core.windows.net/8840118c-b0eb-466f-95b4-3aaa48152688-1/resource/Assets0Images00015.jpg?sv=2017-04-17&sr=b&sig=abAvZxNm9dk1XTqhNXMV%2FGa45%2FLo0JCBI3dVsesI4B0%3D&spr=https&se=2022-12-30T04%3A37%3A15Z&sp=r",
    "MicrosoftTeams-image (1)": "https://docserverpwaprodcin.blob.core.windows.net/8840118c-b0eb-466f-95b4-3aaa48152688-1/resource/Assets0Images00016.png?sv=2017-04-17&sr=b&sig=Sn9WMuRzLEzczgq1fiAw2cTjKQRFz2ouMlEfKOlertE%3D&spr=https&se=2022-12-30T04%3A37%3A15Z&sp=r",
    "MicrosoftTeams-image (2)": "https://docserverpwaprodcin.blob.core.windows.net/8840118c-b0eb-466f-95b4-3aaa48152688-1/resource/Assets0Images00017.png?sv=2017-04-17&sr=b&sig=OnG8UFn38yeRAjuM13PbmC4302gQKBN8tBl6dSS2sts%3D&spr=https&se=2022-12-30T04%3A37%3A15Z&sp=r",
    "MicrosoftTeams-image (3)": "https://docserverpwaprodcin.blob.core.windows.net/8840118c-b0eb-466f-95b4-3aaa48152688-1/resource/Assets0Images00018.png?sv=2017-04-17&sr=b&sig=sarOxoS7Qlzk8zw6FT7VA47h0pBrdM1lF5Sqg82wjb8%3D&spr=https&se=2022-12-30T04%3A37%3A15Z&sp=r",
    "poojatest": "https://docserverpwaprodcin.blob.core.windows.net/8840118c-b0eb-466f-95b4-3aaa48152688-1/resource/Assets0Images00019.PNG?sv=2017-04-17&sr=b&sig=okBDP9WAfAH6gD2UNiZh2eD27ogDmVYCQHiVk3no2L4%3D&spr=https&se=2022-12-30T04%3A37%3A15Z&sp=r",
    "poojatest1": "https://docserverpwaprodcin.blob.core.windows.net/8840118c-b0eb-466f-95b4-3aaa48152688-1/resource/Assets0Images00020.png?sv=2017-04-17&sr=b&sig=7R7ED3iYx7Td4icqC0BTl2z35dcgQAgXhiGs3sibTaU%3D&spr=https&se=2022-12-30T04%3A37%3A15Z&sp=r",
    "priya": "https://docserverpwaprodcin.blob.core.windows.net/8840118c-b0eb-466f-95b4-3aaa48152688-1/resource/Assets0Images00021.PNG?sv=2017-04-17&sr=b&sig=wBXKmZO9Sy6McvDbSNsai2cITKnyT8rpIi0a6dYb9uM%3D&spr=https&se=2022-12-30T04%3A37%3A15Z&sp=r",
    "priyatest": "https://docserverpwaprodcin.blob.core.windows.net/8840118c-b0eb-466f-95b4-3aaa48152688-1/resource/Assets0Images00022.PNG?sv=2017-04-17&sr=b&sig=IBjbAzY2m73QjbkEA8z8kRWGZ1C523l0FSHCi1uSO0o%3D&spr=https&se=2022-12-30T04%3A37%3A15Z&sp=r",
    "priyatest1": "https://docserverpwaprodcin.blob.core.windows.net/8840118c-b0eb-466f-95b4-3aaa48152688-1/resource/Assets0Images00023.png?sv=2017-04-17&sr=b&sig=Ih8rm9YB2sE1zsFK2APvlTR3FDqqXQfeopKdnljiXYk%3D&spr=https&se=2022-12-30T04%3A37%3A15Z&sp=r",
    "Quotes1": "https://docserverpwaprodcin.blob.core.windows.net/8840118c-b0eb-466f-95b4-3aaa48152688-1/resource/Assets0Images00024.png?sv=2017-04-17&sr=b&sig=aA213sgszVAH0qok0Si%2BpkQ4t6%2B3uYjuOE4olMAS6FE%3D&spr=https&se=2022-12-30T04%3A37%3A15Z&sp=r",
    "Quotes2": "https://docserverpwaprodcin.blob.core.windows.net/8840118c-b0eb-466f-95b4-3aaa48152688-1/resource/Assets0Images00025.png?sv=2017-04-17&sr=b&sig=%2BiU65HToOf2gLT9vXzhAVeFHd62KqBWWaA1Did8EPHc%3D&spr=https&se=2022-12-30T04%3A37%3A15Z&sp=r",
    "Rohan Kudav": "https://docserverpwaprodcin.blob.core.windows.net/8840118c-b0eb-466f-95b4-3aaa48152688-1/resource/Assets0Images00026.jpg?sv=2017-04-17&sr=b&sig=I9G%2Fu%2Fr4KIiyJTG1IKfMPsMm1yaIcowGTwZ51IzUrKo%3D&spr=https&se=2022-12-30T04%3A37%3A15Z&sp=r",
    "sanjeev korupolu": "https://docserverpwaprodcin.blob.core.windows.net/8840118c-b0eb-466f-95b4-3aaa48152688-1/resource/Assets0Images00027.jpg?sv=2017-04-17&sr=b&sig=s6nc95gOkkx81KSGsZDlZt8hqPixmDEfaFA9n3ZzRwc%3D&spr=https&se=2022-12-30T04%3A37%3A15Z&sp=r",
    "soundarya cholkar": "https://docserverpwaprodcin.blob.core.windows.net/8840118c-b0eb-466f-95b4-3aaa48152688-1/resource/Assets0Images00028.jpg?sv=2017-04-17&sr=b&sig=k7uePMXgah3%2Boj5Wwiwye5yyxwiifakTI79%2F9UppFYU%3D&spr=https&se=2022-12-30T04%3A37%3A15Z&sp=r",
    "square-facebook": "https://docserverpwaprodcin.blob.core.windows.net/8840118c-b0eb-466f-95b4-3aaa48152688-1/resource/Assets0Images00029.svg?sv=2017-04-17&sr=b&sig=d6MHSrq5ucvKmbUP4tafjqpT2P9ILGmZNnRL7bAwAxs%3D&spr=https&se=2022-12-30T04%3A37%3A15Z&sp=r",
    "square-twitter": "https://docserverpwaprodcin.blob.core.windows.net/8840118c-b0eb-466f-95b4-3aaa48152688-1/resource/Assets0Images00030.svg?sv=2017-04-17&sr=b&sig=OpXeAe1kYeShHVpDBcJnux%2FCf%2Bs4ON66zQMpRpQdhbg%3D&spr=https&se=2022-12-30T04%3A37%3A15Z&sp=r",
    "testomonial": "https://docserverpwaprodcin.blob.core.windows.net/8840118c-b0eb-466f-95b4-3aaa48152688-1/resource/Assets0Images00031.PNG?sv=2017-04-17&sr=b&sig=9LSO46u1ro7QP6fkuT2u%2FQ30ishCi7A0FQrx0qeT0hg%3D&spr=https&se=2022-12-30T04%3A37%3A15Z&sp=r",
    "youtube": "https://docserverpwaprodcin.blob.core.windows.net/8840118c-b0eb-466f-95b4-3aaa48152688-1/resource/Assets0Images00032.svg?sv=2017-04-17&sr=b&sig=G3XGzGoX733r8jK1e4UnPfvvzROcQl%2F3rdljeMPNLNI%3D&spr=https&se=2022-12-30T04%3A37%3A15Z&sp=r"
  },
  "OrderComponentMetadata": {
    "0927d2b0e1b146c68bb9d9479edc1044": 5,
    "62dc4f1561b4448e901618e4647b41b4": 0,
    "923589e162334ba3ac42a49447cb3358": 3,
    "abc5859afff742348a300a44f7269761": 4,
    "f210c8996a1c4890ba04d40592a3d7d0": 2,
    "f519ced9060241e4947d9bc36dcc7f62": 1
  },
  "OrderComponentTemplate": {
    "0927d2b0e1b146c68bb9d9479edc1044": 5,
    "62dc4f1561b4448e901618e4647b41b4": 0,
    "923589e162334ba3ac42a49447cb3358": 3,
    "abc5859afff742348a300a44f7269761": 4,
    "f210c8996a1c4890ba04d40592a3d7d0": 2,
    "f519ced9060241e4947d9bc36dcc7f62": 1
  },
  "OrderDataSource": {
    "Activities": 36,
    "Activity": 10,
    "Blog": 11,
    "Blog_1": 12,
    "BlogComments": 37,
    "BlogsPerMonth": 38,
    "colHorizontalMenu": 39,
    "ColumnChartSample": 13,
    "ComboBoxSample": 14,
    "Comment": 15,
    "Community_1": 16,
    "Community_2": 17,
    "CustomGallerySample": 18,
    "DropdownColumn": 40,
    "DropDownSample": 19,
    "Environment Variable Values": 34,
    "Environment Variable Values\\componentstate": 6,
    "Environment Variable Values\\default.cds_environmentvariablevalue_views": 9,
    "Environment Variable Values\\environmentvariablevalue_statecode": 7,
    "Environment Variable Values\\environmentvariablevalue_statuscode": 8,
    "Environment Variable Values\\ismanaged": 5,
    "Event": 21,
    "Event Track Details": 20,
    "EventCategories": 41,
    "EventStatus": 42,
    "EventStatusAdmin": 54,
    "EventTitle": 43,
    "GetDataURI": 0,
    "GroupUsers": 44,
    "Guild": 25,
    "Guild List": 22,
    "Guild List_1": 24,
    "Guild List1": 23,
    "Guild_1": 35,
    "GuildCommunities": 55,
    "Hours": 45,
    "LegendSample": 26,
    "Like": 27,
    "LineChartSample": 28,
    "ListboxSample": 29,
    "Office365Outlook": 1,
    "Office365Users": 2,
    "Office365Users_1": 3,
    "PieChartSample": 30,
    "Points": 31,
    "Ranks": 46,
    "TopFiveCommunities": 47,
    "TopFivePopularGuilds": 48,
    "TopFiveUsers": 49,
    "UploadFileToDocumentLibrary": 4,
    "User": 32,
    "UserBlog": 50,
    "UserBlogsPerMonth": 51,
    "UserCommunity": 52,
    "userprofile": 53,
    "white_papers": 33
  },
  "OrderGroupControls": {
    "CompositeColumnChart1": {
      "ColumnChart1": 1,
      "Legend2": 2,
      "Title3": 0
    },
    "CompositeColumnChart2": {
      "ColumnChart2": 1,
      "Legend4": 2,
      "Title5": 0
    },
    "CompositeColumnChart2_1": {
      "Legend5_1": 2,
      "Title5_2": 0,
      "Top Communities_1": 1
    },
    "CompositeColumnChart4": {
      "ColumnChart3": 1,
      "Legend10": 2,
      "Title11_1": 0
    },
    "CompositeLineChart1": {
      "Legend1": 2,
      "LineChart1": 1,
      "Title2": 0
    },
    "CompositeLineChart1_1": {
      "Legend1_1": 2,
      "LineChart1_1": 1,
      "Title1_1": 0
    },
    "CompositeLineChart2": {
      "Legend6_1": 2,
      "LineChart2": 1,
      "Title7": 0
    },
    "CompositePieChart3": {
      "Legend6": 2,
      "PieChart3": 1,
      "Title8": 0
    },
    "CompositePieChart4": {
      "Legend9": 2,
      "PieChart4": 1,
      "Title10_1": 0
    },
    "CompositePieChart5": {
      "Legend8": 2,
      "PieChart5": 1,
      "Title10": 0
    },
    "DtopDownDash": {
      "Button5": 1,
      "Rectangle6": 0
    },
    "DtopDownDash_1": {
      "Button5_4": 1,
      "Rectangle6_1": 0
    },
    "DtopDownDash_2": {
      "Button5_5": 1,
      "Rectangle6_2": 0
    },
    "Group1": {
      "Icon9": 5,
      "Image14": 1,
      "Image14_1": 2,
      "Image14_2": 3,
      "Label8": 4,
      "Rectangle4": 0
    },
    "HomeDropDown": {
      "Button1": 1,
      "Button1_2": 2,
      "Button1_3": 3,
      "Button1_4": 4,
      "Button1_5": 5,
      "Rectangle3": 0
    },
    "NavBarGr": {
      "Button17": 2,
      "Button18": 3,
      "Button18_1": 4,
      "Button18_2": 5,
      "Button18_3": 6,
      "Button20_1": 8,
      "Button20_5": 9,
      "Component1_1": 0,
      "Icon3": 7,
      "Rectangle2": 1
    },
    "NavBarGr_1": {
      "Button17_1": 2,
      "Button18_4": 6,
      "Button18_5": 5,
      "Button18_6": 4,
      "Button18_7": 3,
      "Button20_10": 10,
      "Button20_11": 8,
      "Button20_12": 9,
      "Component1_3": 0,
      "Icon3_2": 7,
      "Rectangle2_1": 1
    },
    "NavBarGr_2": {
      "Button17_3": 2,
      "Button18_12": 6,
      "Button18_13": 5,
      "Button18_14": 4,
      "Button18_15": 3,
      "Button20_3": 8,
      "Button20_6": 9,
      "Component1_4": 0,
      "Icon3_3": 7,
      "Rectangle2_3": 1
    },
    "NavBarGr_3": {
      "Button17_4": 2,
      "Button18_16": 6,
      "Button18_17": 5,
      "Button18_18": 4,
      "Button18_19": 3,
      "Button20_7": 9,
      "Button20_8": 8,
      "Component1_2": 0,
      "Icon3_1": 7,
      "Rectangle2_4": 1
    }
  },
  "OrderPcfTemplate": {},
  "OrderTemplate": {},
  "OrderXMLTemplate": {
    "addMedia": 22,
    "arrow": 11,
    "attachments": 25,
    "barChart": 15,
    "button": 2,
    "circle": 10,
    "datepicker": 24,
    "dropdown": 8,
    "fluidGrid": 9,
    "form": 21,
    "gallery": 6,
    "groupContainer": 4,
    "htmlViewer": 19,
    "icon": 3,
    "image": 1,
    "label": 7,
    "legend": 18,
    "lineChart": 17,
    "microsoftStreamPlayback": 12,
    "pdfViewer": 23,
    "pieChart": 16,
    "rectangle": 0,
    "richTextEditor": 20,
    "star": 14,
    "text": 5,
    "timer": 13
  },
  "OverridablePropertiesEntry": {
    "About": {},
    "ActivityDetails": {},
    "AddActivity": {},
    "AddPicture1": {},
    "AddPicture10": {},
    "AddPicture2": {},
    "AddPicture3": {},
    "AddPicture5": {},
    "AddPicture5_1": {},
    "AddPicture6": {},
    "AddPicture7": {},
    "AddPicture8": {},
    "AddPicture9": {},
    "Admin": {},
    "allBlogs": {},
    "AllBlogs": {},
    "App": {},
    "Attachments_DataCard1": {},
    "Attachments_DataCard2": {},
    "Attachments_DataCard2_1": {},
    "Attachments_DataCard2_2": {},
    "Attachments_DataCard4": {},
    "Body1_1": {},
    "Body2": {},
    "btnNext": {},
    "btnPrevious": {},
    "Button1": {},
    "Button1_1": {},
    "Button1_2": {},
    "Button1_3": {},
    "Button1_4": {},
    "Button1_5": {},
    "Button10": {},
    "Button11": {},
    "Button12": {},
    "Button14": {},
    "Button16": {},
    "Button16_1": {},
    "Button17": {},
    "Button17_1": {},
    "Button17_3": {},
    "Button17_4": {},
    "Button18": {},
    "Button18_1": {},
    "Button18_12": {},
    "Button18_13": {},
    "Button18_14": {},
    "Button18_15": {},
    "Button18_16": {},
    "Button18_17": {},
    "Button18_18": {},
    "Button18_19": {},
    "Button18_2": {},
    "Button18_3": {},
    "Button18_4": {},
    "Button18_5": {},
    "Button18_6": {},
    "Button18_7": {},
    "Button2": {},
    "Button2_3": {},
    "Button2_4": {},
    "Button2_5": {},
    "Button2_6": {},
    "Button20_1": {},
    "Button20_10": {},
    "Button20_11": {},
    "Button20_12": {},
    "Button20_3": {},
    "Button20_5": {},
    "Button20_6": {},
    "Button20_7": {},
    "Button20_8": {},
    "Button3": {},
    "Button3_1": {},
    "Button4": {},
    "Button4_1": {},
    "Button5": {},
    "Button5_1": {},
    "Button5_2": {},
    "Button5_3": {},
    "Button5_4": {},
    "Button5_5": {},
    "Button6": {},
    "Button6_1": {},
    "Button7": {},
    "Button8": {},
    "Button8_1": {},
    "Button8_2": {},
    "Button9": {},
    "Canvas1": {},
    "Canvas1_1": {},
    "Canvas10": {},
    "Canvas11": {},
    "Canvas2": {},
    "Canvas3": {},
    "Canvas4": {},
    "Canvas5": {},
    "Canvas6": {},
    "Canvas7": {},
    "Canvas8": {},
    "Canvas9": {},
    "Circle1_1": {},
    "ColumnChart1": {},
    "ColumnChart2": {},
    "ColumnChart3": {},
    "Communities_Column1_1": {},
    "Community": {},
    "CommunityRole_Column1_1": {},
    "Component1": {},
    "Component1_1": {},
    "Component1_2": {},
    "Component1_3": {},
    "Component1_4": {},
    "Component2_1": {},
    "Component3_1": {},
    "CompositeColumnChart1": {},
    "CompositeColumnChart2": {},
    "CompositeColumnChart2_1": {},
    "CompositeColumnChart4": {},
    "CompositeLineChart1": {},
    "CompositeLineChart1_1": {},
    "CompositeLineChart2": {},
    "CompositePieChart3": {},
    "CompositePieChart4": {},
    "CompositePieChart5": {},
    "Container1": {},
    "Container2": {},
    "Container3": {},
    "Container5": {},
    "content": {},
    "content_1": {},
    "createBlog": {},
    "Dashboard": {},
    "DataCard1": {},
    "DataCard10": {},
    "DataCard11": {},
    "DataCard12": {},
    "DataCard13": {},
    "DataCard14": {},
    "DataCard15": {},
    "DataCard16": {},
    "DataCard17": {},
    "DataCard18": {},
    "DataCard19": {},
    "DataCard2": {},
    "DataCard2_1": {},
    "DataCard20": {},
    "DataCard21": {},
    "DataCard22": {},
    "DataCard23": {},
    "DataCard24": {},
    "DataCard25": {},
    "DataCard27": {},
    "DataCard28": {},
    "DataCard29": {},
    "DataCard3": {},
    "DataCard30": {},
    "DataCard31": {},
    "DataCard32": {},
    "DataCard33": {},
    "DataCard4": {},
    "DataCard5": {},
    "DataCard6": {},
    "DataCard7": {},
    "DataCard8": {},
    "DataCard9": {},
    "DataCardKey1": {},
    "DataCardKey10": {},
    "DataCardKey11": {},
    "DataCardKey12": {},
    "DataCardKey14": {},
    "DataCardKey15": {},
    "DataCardKey17": {},
    "DataCardKey18": {},
    "DataCardKey18_1": {},
    "DataCardKey19": {},
    "DataCardKey2": {},
    "DataCardKey20": {},
    "DataCardKey21": {},
    "DataCardKey22": {},
    "DataCardKey23": {},
    "DataCardKey24": {},
    "DataCardKey25": {},
    "DataCardKey26": {},
    "DataCardKey27": {},
    "DataCardKey29": {},
    "DataCardKey3": {},
    "DataCardKey31": {},
    "DataCardKey32": {},
    "DataCardKey33": {},
    "DataCardKey34": {},
    "DataCardKey35": {},
    "DataCardKey4": {},
    "DataCardKey4_1": {},
    "DataCardKey43": {},
    "DataCardKey5": {},
    "DataCardKey6": {},
    "DataCardKey6_1": {},
    "DataCardKey7": {},
    "DataCardKey8": {},
    "DataCardKey9": {},
    "DataCardValue1": {},
    "DataCardValue11": {},
    "DataCardValue12": {},
    "DataCardValue13": {},
    "DataCardValue14": {},
    "DataCardValue15": {},
    "DataCardValue16": {},
    "DataCardValue17": {},
    "DataCardValue17_1": {},
    "DataCardValue18": {},
    "DataCardValue19": {},
    "DataCardValue20": {},
    "DataCardValue21": {},
    "DataCardValue23": {},
    "DataCardValue25": {},
    "DataCardValue26": {},
    "DataCardValue27": {},
    "DataCardValue28": {},
    "DataCardValue3_1": {},
    "DataCardValue31": {},
    "DataCardValue4_1": {},
    "DataCardValue42": {},
    "DataCardValue5_1": {},
    "DataCardValue8": {},
    "DataCardValue8_1": {},
    "DataCardValue9": {},
    "DataTable1": {},
    "DataTable1_1": {},
    "DataTable2": {},
    "DataTable3": {},
    "DataTable3_1": {},
    "Date_DataCard1": {},
    "Date_DataCard2": {},
    "DateofEvent_Column1_1": {},
    "DatePicker1": {},
    "DatePicker1_1": {},
    "ddPageSize": {},
    "Description_DataCard1": {},
    "Description_DataCard3": {},
    "Designation1_DataCard1": {},
    "detailBlog": {},
    "detailBlog2": {},
    "Dropdown1": {},
    "Dropdown1_1": {},
    "Dropdown2": {},
    "Dropdown2_1": {},
    "Dropdown2_2": {},
    "Dropdown3": {},
    "Dropdown4": {},
    "Dropdown5": {},
    "Dropdown6": {},
    "DtopDownDash": {},
    "DtopDownDash_1": {},
    "DtopDownDash_2": {},
    "editBlog": {},
    "ErrorMessage1": {},
    "ErrorMessage10": {},
    "ErrorMessage11": {},
    "ErrorMessage12": {},
    "ErrorMessage14": {},
    "ErrorMessage15": {},
    "ErrorMessage17": {},
    "ErrorMessage18": {},
    "ErrorMessage18_1": {},
    "ErrorMessage19": {},
    "ErrorMessage2": {},
    "ErrorMessage20": {},
    "ErrorMessage21": {},
    "ErrorMessage22": {},
    "ErrorMessage23": {},
    "ErrorMessage24": {},
    "ErrorMessage25": {},
    "ErrorMessage26": {},
    "ErrorMessage27": {},
    "ErrorMessage29": {},
    "ErrorMessage3": {},
    "ErrorMessage31": {},
    "ErrorMessage32": {},
    "ErrorMessage33": {},
    "ErrorMessage34": {},
    "ErrorMessage35": {},
    "ErrorMessage4": {},
    "ErrorMessage4_1": {},
    "ErrorMessage43": {},
    "ErrorMessage5": {},
    "ErrorMessage6": {},
    "ErrorMessage6_1": {},
    "ErrorMessage7": {},
    "ErrorMessage8": {},
    "ErrorMessage9": {},
    "EventDetails": {},
    "EventEdit": {},
    "EventForm": {},
    "FAQs": {},
    "Feedback": {},
    "Feedback_Column1": {},
    "FileUpload": {},
    "Footer": {},
    "Form1_1": {},
    "Form2": {},
    "Form2_1": {},
    "Form3": {},
    "Form3_1": {},
    "Form3_2": {},
    "Form4": {},
    "Form5": {},
    "FullDescription_DataCard1": {},
    "Gallery1_1": {},
    "Gallery11": {},
    "Gallery12": {},
    "Gallery18": {},
    "Gallery18_1": {},
    "Gallery2": {},
    "Gallery2_1": {},
    "Gallery3": {},
    "Gallery4": {},
    "Gallery7": {},
    "Gallery9": {},
    "galleryTemplate1": {},
    "galleryTemplate1_1": {},
    "galleryTemplate10": {},
    "galleryTemplate11": {},
    "galleryTemplate12": {},
    "galleryTemplate18": {},
    "galleryTemplate18_1": {},
    "galleryTemplate2": {},
    "galleryTemplate2_1": {},
    "galleryTemplate2_2": {},
    "galleryTemplate3_1": {},
    "galleryTemplate4": {},
    "galleryTemplate5": {},
    "galleryTemplate7": {},
    "galPaginated": {},
    "Group1": {},
    "Guild Form": {},
    "Home": {},
    "HomeDropDown": {},
    "HomeImage": {},
    "HtmlText2": {},
    "HtmlText3": {},
    "Icon1": {},
    "Icon10": {},
    "Icon10_1": {},
    "Icon11": {},
    "Icon12": {},
    "Icon13": {},
    "Icon14": {},
    "Icon15": {},
    "Icon16": {},
    "Icon17": {},
    "Icon18": {},
    "Icon19": {},
    "Icon2": {},
    "Icon2_1": {},
    "Icon20": {},
    "Icon21": {},
    "Icon22": {},
    "Icon23": {},
    "Icon24": {},
    "Icon25": {},
    "Icon26": {},
    "Icon27": {},
    "Icon27_1": {},
    "Icon28": {},
    "Icon3": {},
    "Icon3_1": {},
    "Icon3_2": {},
    "Icon3_3": {},
    "Icon3_4": {},
    "Icon3_5": {},
    "Icon3_6": {},
    "Icon3_7": {},
    "Icon30": {},
    "Icon4": {},
    "Icon4_2": {},
    "Icon5": {},
    "Icon5_1": {},
    "Icon5_2": {},
    "Icon5_3": {},
    "Icon6": {},
    "Icon7": {},
    "Icon7_1": {},
    "Icon8": {},
    "Icon9": {},
    "iconNextMonth1_1": {},
    "iconPrevMonth1_1": {},
    "Image_DataCard1": {},
    "Image_DataCard2": {},
    "Image_DataCard3": {},
    "Image1": {},
    "Image1_1": {},
    "Image1_DataCard1": {},
    "Image10": {},
    "Image10_1": {},
    "Image10_2": {},
    "Image10_3": {},
    "Image10_4": {},
    "Image11": {},
    "Image11_1": {},
    "Image11_2": {},
    "Image11_3": {},
    "Image11_4": {},
    "Image12": {},
    "Image13": {},
    "Image14": {},
    "Image14_1": {},
    "Image14_2": {},
    "Image15": {},
    "Image16": {},
    "Image17": {},
    "Image18": {},
    "Image2": {},
    "Image2_1": {},
    "Image20": {},
    "Image21": {},
    "Image22": {},
    "Image23": {},
    "Image24": {},
    "Image25": {},
    "Image25_1": {},
    "Image25_2": {},
    "Image26": {},
    "Image27": {},
    "Image28": {},
    "Image29": {},
    "Image3": {},
    "Image3_1": {},
    "Image3_2": {},
    "Image30": {},
    "Image31": {},
    "Image4": {},
    "Image4_1": {},
    "Image5": {},
    "Image5_1": {},
    "Image6": {},
    "Image7": {},
    "Image7_1": {},
    "Image8": {},
    "Image8_1": {},
    "Image9": {},
    "Label1": {},
    "Label1_1": {},
    "Label10": {},
    "Label10_1": {},
    "Label11": {},
    "Label11_1": {},
    "Label11_2": {},
    "Label11_3": {},
    "Label11_4": {},
    "Label11_5": {},
    "Label12": {},
    "Label12_1": {},
    "Label12_2": {},
    "Label13": {},
    "Label13_1": {},
    "Label13_2": {},
    "Label14": {},
    "Label15": {},
    "Label16": {},
    "Label16_1": {},
    "Label17": {},
    "Label17_1": {},
    "Label18": {},
    "Label18_1": {},
    "Label19": {},
    "Label2": {},
    "Label2_1": {},
    "Label2_2": {},
    "Label2_4": {},
    "Label2_5": {},
    "Label2_6": {},
    "Label2_7": {},
    "Label20": {},
    "Label21": {},
    "Label21_1": {},
    "Label22": {},
    "Label22_1": {},
    "Label23": {},
    "Label24": {},
    "Label24_1": {},
    "Label25": {},
    "Label26": {},
    "Label26_1": {},
    "Label27": {},
    "Label28": {},
    "Label28_1": {},
    "Label29": {},
    "Label29_1": {},
    "Label3": {},
    "Label3_1": {},
    "Label3_4": {},
    "Label3_5": {},
    "Label3_6": {},
    "Label3_7": {},
    "Label30": {},
    "Label31": {},
    "Label32": {},
    "Label33": {},
    "Label34": {},
    "Label35": {},
    "Label36": {},
    "Label37": {},
    "Label38": {},
    "Label39": {},
    "Label4": {},
    "Label4_1": {},
    "Label4_3": {},
    "Label40": {},
    "Label41": {},
    "Label43": {},
    "Label44": {},
    "Label45": {},
    "Label5": {},
    "Label5_1": {},
    "Label5_2": {},
    "Label5_3": {},
    "Label6": {},
    "Label6_1": {},
    "Label6_2": {},
    "Label6_3": {},
    "Label6_4": {},
    "Label6_5": {},
    "Label6_7": {},
    "Label7": {},
    "Label7_1": {},
    "Label8": {},
    "Label8_1": {},
    "Label8_2": {},
    "Label9": {},
    "Label9_1": {},
    "Label9_2": {},
    "Label9_3": {},
    "Label9_4": {},
    "Label9_5": {},
    "LblAppName1": {},
    "LblAppName10": {},
    "LblAppName2": {},
    "LblAppName3": {},
    "LblAppName5": {},
    "LblAppName6": {},
    "LblAppName7": {},
    "LblAppName8": {},
    "LblAppName9": {},
    "LblMonthSelected1_1": {},
    "lblPagination": {},
    "Legend1": {},
    "Legend1_1": {},
    "Legend10": {},
    "Legend2": {},
    "Legend4": {},
    "Legend5_1": {},
    "Legend6": {},
    "Legend6_1": {},
    "Legend8": {},
    "Legend9": {},
    "LineChart1": {},
    "LineChart1_1": {},
    "LineChart2": {},
    "Link_DataCard1": {},
    "Members_Column1": {},
    "MicrosoftStream2": {},
    "MonthDayGallery1_1": {},
    "Name_Column1": {},
    "Name_DataCard1": {},
    "Name_DataCard2": {},
    "NavBar": {},
    "NavBarGr": {},
    "NavBarGr_1": {},
    "NavBarGr_2": {},
    "NavBarGr_3": {},
    "NextArrow2": {},
    "NextArrow20": {},
    "NextArrow20_1": {},
    "NextArrow6": {},
    "No_Column1": {},
    "PdfViewer1": {},
    "PieChart3": {},
    "PieChart4": {},
    "PieChart5": {},
    "Points_Column1": {},
    "Polestar1_DataCard1": {},
    "Profile": {},
    "Rectangle1": {},
    "Rectangle2": {},
    "Rectangle2_1": {},
    "Rectangle2_3": {},
    "Rectangle2_4": {},
    "Rectangle3": {},
    "Rectangle4": {},
    "Rectangle6": {},
    "Rectangle6_1": {},
    "Rectangle6_2": {},
    "Rectangle8": {},
    "RectQuickActionBar1": {},
    "RectQuickActionBar1_2": {},
    "RectQuickActionBar10": {},
    "RectQuickActionBar11": {},
    "RectQuickActionBar12": {},
    "RectQuickActionBar13": {},
    "RectQuickActionBar2": {},
    "RectQuickActionBar3": {},
    "RectQuickActionBar4": {},
    "RectQuickActionBar5": {},
    "RectQuickActionBar6": {},
    "RectQuickActionBar7": {},
    "RectQuickActionBar8": {},
    "RectQuickActionBar9": {},
    "RichTextEditor1": {},
    "Separator1": {},
    "Separator2": {},
    "Separator22": {},
    "Separator22_1": {},
    "Separator5": {},
    "Separator6_1": {},
    "Separator7": {},
    "Separator9": {},
    "shareIt": {},
    "Short Description_DataCard2": {},
    "Star1_1": {},
    "StarVisible1": {},
    "StarVisible10": {},
    "StarVisible11": {},
    "StarVisible12": {},
    "StarVisible14": {},
    "StarVisible15": {},
    "StarVisible17": {},
    "StarVisible18": {},
    "StarVisible18_1": {},
    "StarVisible19": {},
    "StarVisible2": {},
    "StarVisible20": {},
    "StarVisible21": {},
    "StarVisible22": {},
    "StarVisible23": {},
    "StarVisible24": {},
    "StarVisible25": {},
    "StarVisible26": {},
    "StarVisible27": {},
    "StarVisible29": {},
    "StarVisible3": {},
    "StarVisible31": {},
    "StarVisible32": {},
    "StarVisible33": {},
    "StarVisible34": {},
    "StarVisible35": {},
    "StarVisible4": {},
    "StarVisible4_1": {},
    "StarVisible43": {},
    "StarVisible5": {},
    "StarVisible6": {},
    "StarVisible6_1": {},
    "StarVisible7": {},
    "StarVisible8": {},
    "StarVisible9": {},
    "Subcircle1_1": {},
    "Subtitle1": {},
    "Subtitle2": {},
    "Subtitle20": {},
    "Subtitle20_1": {},
    "Subtitle6": {},
    "Subtitle7_1": {},
    "Subtitle8": {},
    "TextInput1": {},
    "TextInput1_1": {},
    "TextInput10": {},
    "TextInput11": {},
    "TextInput2": {},
    "TextInput3": {},
    "TextInput3_1": {},
    "TextInput3_2": {},
    "TextInput4": {},
    "TextInput4_1": {},
    "TextInput5": {},
    "TextInput6": {},
    "TextInput7": {},
    "TextInput9": {},
    "TextInput9_1": {},
    "Timer1": {},
    "title": {},
    "title_1": {},
    "Title_Column1": {},
    "Title_Column2_1": {},
    "Title_DataCard1": {},
    "Title_DataCard2": {},
    "Title_DataCard4": {},
    "Title1": {},
    "Title1_1": {},
    "Title1_2": {},
    "Title10": {},
    "Title10_1": {},
    "Title11": {},
    "Title11_1": {},
    "Title13": {},
    "Title18": {},
    "Title2": {},
    "Title2_1": {},
    "Title2_2": {},
    "Title26": {},
    "Title26_1": {},
    "Title3": {},
    "Title3_1": {},
    "Title4": {},
    "Title5": {},
    "Title5_2": {},
    "Title7": {},
    "Title8": {},
    "Title8_1": {},
    "Top Communities_1": {},
    "Torch Bearers1_DataCard1": {},
    "Torch Bearers2_DataCard1": {},
    "Torch Bearers3_DataCard1": {},
    "TorchImage1_DataCard1": {},
    "TorchImage2_DataCard1": {},
    "TorchImage3_DataCard1": {},
    "Trend Setters1_DataCard1": {},
    "Trend Setters2_DataCard1": {},
    "Trend Setters3_DataCard2": {},
    "TrendImage1_DataCard1": {},
    "TrendImage2_DataCard1": {},
    "TrendImage3_DataCard1": {},
    "UpcomingGuild": {},
    "UpcomingGuild_1": {},
    "UserName": {},
    "UserName_1": {},
    "UserName_Column1": {},
    "WeekdayGallery1_1": {},
    "WhitePapers": {}
  },
  "PCFDynamicSchemaForIRRetrievalEntry": {},
  "PublishOrderIndices": {
    "About": 1,
    "ActivityDetails": 42,
    "AddActivity": 73,
    "AddPicture1": 154,
    "AddPicture10": 199,
    "AddPicture2": 294,
    "AddPicture3": 388,
    "AddPicture5": 160,
    "AddPicture5_1": 133,
    "AddPicture6": 205,
    "AddPicture7": 166,
    "AddPicture8": 187,
    "AddPicture9": 193,
    "Admin": 110,
    "allBlogs": 167,
    "AllBlogs": 162,
    "App": 0,
    "Attachments_DataCard1": 207,
    "Attachments_DataCard2": 466,
    "Attachments_DataCard2_1": 579,
    "Attachments_DataCard2_2": 651,
    "Attachments_DataCard4": 235,
    "Body1_1": 518,
    "Body2": 443,
    "btnNext": 40,
    "btnPrevious": 39,
    "Button1": 93,
    "Button1_1": 476,
    "Button1_2": 72,
    "Button1_3": 98,
    "Button1_4": 89,
    "Button1_5": 78,
    "Button10": 376,
    "Button11": 323,
    "Button12": 690,
    "Button14": 472,
    "Button16": 693,
    "Button16_1": 692,
    "Button17": 70,
    "Button17_1": 425,
    "Button17_3": 540,
    "Button17_4": 318,
    "Button18": 80,
    "Button18_1": 88,
    "Button18_12": 544,
    "Button18_13": 543,
    "Button18_14": 542,
    "Button18_15": 541,
    "Button18_16": 335,
    "Button18_17": 327,
    "Button18_18": 326,
    "Button18_19": 321,
    "Button18_2": 90,
    "Button18_3": 92,
    "Button18_4": 429,
    "Button18_5": 428,
    "Button18_6": 427,
    "Button18_7": 426,
    "Button2": 332,
    "Button2_3": 673,
    "Button2_4": 489,
    "Button2_5": 671,
    "Button2_6": 672,
    "Button20_1": 4,
    "Button20_10": 393,
    "Button20_11": 394,
    "Button20_12": 392,
    "Button20_3": 497,
    "Button20_5": 3,
    "Button20_6": 496,
    "Button20_7": 302,
    "Button20_8": 303,
    "Button3": 668,
    "Button3_1": 516,
    "Button4": 240,
    "Button4_1": 515,
    "Button5": 77,
    "Button5_1": 553,
    "Button5_2": 587,
    "Button5_3": 212,
    "Button5_4": 502,
    "Button5_5": 319,
    "Button6": 298,
    "Button6_1": 577,
    "Button7": 368,
    "Button8": 369,
    "Button8_1": 517,
    "Button8_2": 656,
    "Button9": 436,
    "Canvas1": 9,
    "Canvas1_1": 246,
    "Canvas10": 588,
    "Canvas11": 630,
    "Canvas2": 277,
    "Canvas3": 433,
    "Canvas4": 282,
    "Canvas5": 397,
    "Canvas6": 503,
    "Canvas7": 341,
    "Canvas8": 373,
    "Canvas9": 557,
    "Circle1_1": 38,
    "ColumnChart1": 404,
    "ColumnChart2": 413,
    "ColumnChart3": 609,
    "Communities_Column1_1": 625,
    "Community": 206,
    "CommunityRole_Column1_1": 626,
    "Component1": 9,
    "Component1_1": 1,
    "Component1_2": 300,
    "Component1_3": 391,
    "Component1_4": 494,
    "Component2_1": 11,
    "Component3_1": 14,
    "CompositeColumnChart1": 402,
    "CompositeColumnChart2": 410,
    "CompositeColumnChart2_1": 522,
    "CompositeColumnChart4": 603,
    "CompositeLineChart1": 399,
    "CompositeLineChart1_1": 525,
    "CompositeLineChart2": 607,
    "CompositePieChart3": 411,
    "CompositePieChart4": 605,
    "CompositePieChart5": 417,
    "Container1": 674,
    "Container2": 306,
    "Container3": 81,
    "Container5": 60,
    "content": 289,
    "content_1": 382,
    "createBlog": 251,
    "Dashboard": 272,
    "DataCard1": 48,
    "DataCard10": 283,
    "DataCard11": 398,
    "DataCard12": 407,
    "DataCard13": 13,
    "DataCard14": 349,
    "DataCard15": 374,
    "DataCard16": 416,
    "DataCard17": 351,
    "DataCard18": 434,
    "DataCard19": 504,
    "DataCard2": 17,
    "DataCard2_1": 247,
    "DataCard20": 358,
    "DataCard21": 347,
    "DataCard22": 520,
    "DataCard23": 255,
    "DataCard24": 558,
    "DataCard25": 263,
    "DataCard27": 589,
    "DataCard28": 631,
    "DataCard29": 602,
    "DataCard3": 45,
    "DataCard30": 615,
    "DataCard31": 622,
    "DataCard32": 534,
    "DataCard33": 270,
    "DataCard4": 52,
    "DataCard5": 55,
    "DataCard6": 42,
    "DataCard7": 278,
    "DataCard8": 10,
    "DataCard9": 342,
    "DataCardKey1": 106,
    "DataCardKey10": 197,
    "DataCardKey11": 137,
    "DataCardKey12": 142,
    "DataCardKey14": 131,
    "DataCardKey15": 203,
    "DataCardKey17": 209,
    "DataCardKey18": 448,
    "DataCardKey18_1": 653,
    "DataCardKey19": 217,
    "DataCardKey2": 152,
    "DataCardKey20": 222,
    "DataCardKey21": 227,
    "DataCardKey22": 232,
    "DataCardKey23": 237,
    "DataCardKey24": 453,
    "DataCardKey25": 458,
    "DataCardKey26": 463,
    "DataCardKey27": 468,
    "DataCardKey29": 175,
    "DataCardKey3": 111,
    "DataCardKey31": 147,
    "DataCardKey32": 660,
    "DataCardKey33": 116,
    "DataCardKey34": 170,
    "DataCardKey35": 180,
    "DataCardKey4": 158,
    "DataCardKey4_1": 121,
    "DataCardKey43": 582,
    "DataCardKey5": 386,
    "DataCardKey6": 164,
    "DataCardKey6_1": 126,
    "DataCardKey7": 296,
    "DataCardKey8": 185,
    "DataCardKey9": 191,
    "DataCardValue1": 107,
    "DataCardValue11": 210,
    "DataCardValue12": 449,
    "DataCardValue13": 454,
    "DataCardValue14": 459,
    "DataCardValue15": 464,
    "DataCardValue16": 469,
    "DataCardValue17": 218,
    "DataCardValue17_1": 654,
    "DataCardValue18": 223,
    "DataCardValue19": 228,
    "DataCardValue20": 233,
    "DataCardValue21": 238,
    "DataCardValue23": 176,
    "DataCardValue25": 148,
    "DataCardValue26": 117,
    "DataCardValue27": 171,
    "DataCardValue28": 181,
    "DataCardValue3_1": 112,
    "DataCardValue31": 659,
    "DataCardValue4_1": 122,
    "DataCardValue42": 580,
    "DataCardValue5_1": 127,
    "DataCardValue8": 138,
    "DataCardValue8_1": 488,
    "DataCardValue9": 143,
    "DataTable1": 419,
    "DataTable1_1": 624,
    "DataTable2": 531,
    "DataTable3": 536,
    "DataTable3_1": 618,
    "Date_DataCard1": 461,
    "Date_DataCard2": 230,
    "DateofEvent_Column1_1": 620,
    "DatePicker1": 550,
    "DatePicker1_1": 641,
    "ddPageSize": 25,
    "Description_DataCard1": 451,
    "Description_DataCard3": 220,
    "Designation1_DataCard1": 124,
    "detailBlog": 313,
    "detailBlog2": 348,
    "Dropdown1": 325,
    "Dropdown1_1": 617,
    "Dropdown2": 287,
    "Dropdown2_1": 380,
    "Dropdown2_2": 635,
    "Dropdown3": 636,
    "Dropdown4": 642,
    "Dropdown5": 647,
    "Dropdown6": 508,
    "DtopDownDash": 76,
    "DtopDownDash_1": 501,
    "DtopDownDash_2": 317,
    "editBlog": 350,
    "ErrorMessage1": 108,
    "ErrorMessage10": 200,
    "ErrorMessage11": 139,
    "ErrorMessage12": 144,
    "ErrorMessage14": 134,
    "ErrorMessage15": 206,
    "ErrorMessage17": 211,
    "ErrorMessage18": 450,
    "ErrorMessage18_1": 655,
    "ErrorMessage19": 219,
    "ErrorMessage2": 155,
    "ErrorMessage20": 224,
    "ErrorMessage21": 229,
    "ErrorMessage22": 234,
    "ErrorMessage23": 239,
    "ErrorMessage24": 455,
    "ErrorMessage25": 460,
    "ErrorMessage26": 465,
    "ErrorMessage27": 470,
    "ErrorMessage29": 177,
    "ErrorMessage3": 113,
    "ErrorMessage31": 149,
    "ErrorMessage32": 662,
    "ErrorMessage33": 118,
    "ErrorMessage34": 172,
    "ErrorMessage35": 182,
    "ErrorMessage4": 161,
    "ErrorMessage4_1": 123,
    "ErrorMessage43": 583,
    "ErrorMessage5": 389,
    "ErrorMessage6": 167,
    "ErrorMessage6_1": 128,
    "ErrorMessage7": 297,
    "ErrorMessage8": 188,
    "ErrorMessage9": 194,
    "EventDetails": 371,
    "EventEdit": 382,
    "EventForm": 411,
    "FAQs": 440,
    "Feedback": 443,
    "Feedback_Column1": 621,
    "FileUpload": 453,
    "Footer": 14,
    "Form1_1": 103,
    "Form2": 291,
    "Form2_1": 650,
    "Form3": 383,
    "Form3_1": 578,
    "Form3_2": 657,
    "Form4": 214,
    "Form5": 445,
    "FullDescription_DataCard1": 114,
    "Gallery1_1": 477,
    "Gallery11": 686,
    "Gallery12": 688,
    "Gallery18": 64,
    "Gallery18_1": 310,
    "Gallery2": 437,
    "Gallery2_1": 511,
    "Gallery3": 271,
    "Gallery4": 328,
    "Gallery7": 359,
    "Gallery9": 83,
    "galleryTemplate1": 19,
    "galleryTemplate1_1": 478,
    "galleryTemplate10": 84,
    "galleryTemplate11": 687,
    "galleryTemplate12": 689,
    "galleryTemplate18": 65,
    "galleryTemplate18_1": 311,
    "galleryTemplate2": 438,
    "galleryTemplate2_1": 32,
    "galleryTemplate2_2": 512,
    "galleryTemplate3_1": 35,
    "galleryTemplate4": 329,
    "galleryTemplate5": 272,
    "galleryTemplate7": 360,
    "galPaginated": 18,
    "Group1": 96,
    "Guild Form": 457,
    "Home": 569,
    "HomeDropDown": 73,
    "HomeImage": 24,
    "HtmlText2": 350,
    "HtmlText3": 430,
    "Icon1": 339,
    "Icon10": 356,
    "Icon10_1": 568,
    "Icon11": 23,
    "Icon12": 340,
    "Icon13": 352,
    "Icon14": 324,
    "Icon15": 281,
    "Icon16": 372,
    "Icon17": 435,
    "Icon18": 243,
    "Icon19": 471,
    "Icon2": 664,
    "Icon2_1": 475,
    "Icon20": 82,
    "Icon21": 440,
    "Icon22": 691,
    "Icon23": 442,
    "Icon24": 492,
    "Icon25": 338,
    "Icon26": 24,
    "Icon27": 63,
    "Icon27_1": 309,
    "Icon28": 586,
    "Icon3": 7,
    "Icon3_1": 304,
    "Icon3_2": 396,
    "Icon3_3": 498,
    "Icon3_4": 6,
    "Icon3_5": 8,
    "Icon3_6": 499,
    "Icon3_7": 305,
    "Icon30": 0,
    "Icon4": 546,
    "Icon4_2": 482,
    "Icon5": 61,
    "Icon5_1": 510,
    "Icon5_2": 629,
    "Icon5_3": 307,
    "Icon6": 27,
    "Icon7": 213,
    "Icon7_1": 556,
    "Icon8": 102,
    "Icon9": 97,
    "iconNextMonth1_1": 30,
    "iconPrevMonth1_1": 29,
    "Image_DataCard1": 201,
    "Image_DataCard2": 292,
    "Image_DataCard3": 384,
    "Image1": 670,
    "Image1_1": 685,
    "Image1_DataCard1": 129,
    "Image10": 50,
    "Image10_1": 266,
    "Image10_2": 264,
    "Image10_3": 265,
    "Image10_4": 51,
    "Image11": 682,
    "Image11_1": 678,
    "Image11_2": 679,
    "Image11_3": 680,
    "Image11_4": 559,
    "Image12": 56,
    "Image13": 57,
    "Image14": 99,
    "Image14_1": 100,
    "Image14_2": 101,
    "Image15": 330,
    "Image16": 355,
    "Image17": 343,
    "Image18": 387,
    "Image2": 683,
    "Image2_1": 479,
    "Image20": 132,
    "Image21": 204,
    "Image22": 59,
    "Image23": 348,
    "Image24": 361,
    "Image25": 695,
    "Image25_1": 696,
    "Image25_2": 697,
    "Image26": 5,
    "Image27": 159,
    "Image28": 165,
    "Image29": 186,
    "Image3": 20,
    "Image3_1": 248,
    "Image3_2": 258,
    "Image30": 192,
    "Image31": 198,
    "Image4": 153,
    "Image4_1": 259,
    "Image5": 666,
    "Image5_1": 257,
    "Image6": 58,
    "Image7": 677,
    "Image7_1": 593,
    "Image8": 293,
    "Image8_1": 506,
    "Image9": 250,
    "Label1": 46,
    "Label1_1": 484,
    "Label10": 638,
    "Label10_1": 507,
    "Label11": 284,
    "Label11_1": 288,
    "Label11_2": 377,
    "Label11_3": 381,
    "Label11_4": 548,
    "Label11_5": 640,
    "Label12": 245,
    "Label12_1": 551,
    "Label12_2": 639,
    "Label13": 244,
    "Label13_1": 521,
    "Label13_2": 649,
    "Label14": 490,
    "Label15": 344,
    "Label16": 346,
    "Label16_1": 560,
    "Label17": 345,
    "Label17_1": 561,
    "Label18": 353,
    "Label18_1": 562,
    "Label19": 254,
    "Label2": 669,
    "Label2_1": 505,
    "Label2_2": 483,
    "Label2_4": 595,
    "Label2_5": 591,
    "Label2_6": 598,
    "Label2_7": 600,
    "Label20": 694,
    "Label21": 354,
    "Label21_1": 563,
    "Label22": 366,
    "Label22_1": 564,
    "Label23": 286,
    "Label24": 367,
    "Label24_1": 565,
    "Label25": 290,
    "Label26": 379,
    "Label26_1": 566,
    "Label27": 252,
    "Label28": 375,
    "Label28_1": 567,
    "Label29": 249,
    "Label29_1": 251,
    "Label3": 675,
    "Label3_1": 487,
    "Label3_4": 592,
    "Label3_5": 596,
    "Label3_6": 601,
    "Label3_7": 597,
    "Label30": 253,
    "Label31": 535,
    "Label32": 569,
    "Label33": 573,
    "Label34": 570,
    "Label35": 571,
    "Label36": 574,
    "Label37": 576,
    "Label38": 575,
    "Label39": 572,
    "Label4": 676,
    "Label4_1": 616,
    "Label4_3": 623,
    "Label40": 273,
    "Label41": 274,
    "Label43": 26,
    "Label44": 276,
    "Label45": 275,
    "Label5": 681,
    "Label5_1": 256,
    "Label5_2": 590,
    "Label5_3": 644,
    "Label6": 12,
    "Label6_1": 599,
    "Label6_2": 645,
    "Label6_3": 646,
    "Label6_4": 260,
    "Label6_5": 261,
    "Label6_7": 262,
    "Label7": 491,
    "Label7_1": 632,
    "Label8": 95,
    "Label8_1": 547,
    "Label8_2": 633,
    "Label9": 634,
    "Label9_1": 269,
    "Label9_2": 268,
    "Label9_3": 267,
    "Label9_4": 509,
    "Label9_5": 545,
    "LblAppName1": 91,
    "LblAppName10": 628,
    "LblAppName2": 432,
    "LblAppName3": 280,
    "LblAppName5": 474,
    "LblAppName6": 337,
    "LblAppName7": 371,
    "LblAppName8": 555,
    "LblAppName9": 585,
    "LblMonthSelected1_1": 28,
    "lblPagination": 41,
    "Legend1": 405,
    "Legend1_1": 529,
    "Legend10": 613,
    "Legend2": 406,
    "Legend4": 415,
    "Legend5_1": 528,
    "Legend6": 414,
    "Legend6_1": 614,
    "Legend8": 423,
    "Legend9": 612,
    "LineChart1": 403,
    "LineChart1_1": 527,
    "LineChart2": 611,
    "Link_DataCard1": 658,
    "Members_Column1": 538,
    "MicrosoftStream2": 49,
    "MonthDayGallery1_1": 34,
    "Name_Column1": 420,
    "Name_DataCard1": 456,
    "Name_DataCard2": 225,
    "NavBar": 26,
    "NavBarGr": 2,
    "NavBarGr_1": 395,
    "NavBarGr_2": 495,
    "NavBarGr_3": 301,
    "NextArrow2": 481,
    "NextArrow20": 67,
    "NextArrow20_1": 313,
    "NextArrow6": 85,
    "No_Column1": 533,
    "PdfViewer1": 486,
    "PieChart3": 412,
    "PieChart4": 610,
    "PieChart5": 422,
    "Points_Column1": 421,
    "Polestar1_DataCard1": 119,
    "Profile": 660,
    "Rectangle1": 365,
    "Rectangle2": 74,
    "Rectangle2_1": 424,
    "Rectangle2_3": 539,
    "Rectangle2_4": 320,
    "Rectangle3": 71,
    "Rectangle4": 94,
    "Rectangle6": 75,
    "Rectangle6_1": 500,
    "Rectangle6_2": 316,
    "Rectangle8": 684,
    "RectQuickActionBar1": 0,
    "RectQuickActionBar1_2": 242,
    "RectQuickActionBar10": 473,
    "RectQuickActionBar11": 554,
    "RectQuickActionBar12": 584,
    "RectQuickActionBar13": 627,
    "RectQuickActionBar2": 241,
    "RectQuickActionBar3": 431,
    "RectQuickActionBar4": 279,
    "RectQuickActionBar5": 390,
    "RectQuickActionBar6": 299,
    "RectQuickActionBar7": 336,
    "RectQuickActionBar8": 370,
    "RectQuickActionBar9": 493,
    "RichTextEditor1": 552,
    "Separator1": 334,
    "Separator2": 485,
    "Separator22": 69,
    "Separator22_1": 315,
    "Separator5": 444,
    "Separator6_1": 519,
    "Separator7": 364,
    "Separator9": 87,
    "shareIt": 704,
    "Short Description_DataCard2": 109,
    "Star1_1": 594,
    "StarVisible1": 105,
    "StarVisible10": 196,
    "StarVisible11": 136,
    "StarVisible12": 141,
    "StarVisible14": 130,
    "StarVisible15": 202,
    "StarVisible17": 208,
    "StarVisible18": 447,
    "StarVisible18_1": 652,
    "StarVisible19": 216,
    "StarVisible2": 151,
    "StarVisible20": 221,
    "StarVisible21": 226,
    "StarVisible22": 231,
    "StarVisible23": 236,
    "StarVisible24": 452,
    "StarVisible25": 457,
    "StarVisible26": 462,
    "StarVisible27": 467,
    "StarVisible29": 174,
    "StarVisible3": 110,
    "StarVisible31": 146,
    "StarVisible32": 661,
    "StarVisible33": 115,
    "StarVisible34": 169,
    "StarVisible35": 179,
    "StarVisible4": 157,
    "StarVisible4_1": 120,
    "StarVisible43": 581,
    "StarVisible5": 385,
    "StarVisible6": 163,
    "StarVisible6_1": 125,
    "StarVisible7": 295,
    "StarVisible8": 184,
    "StarVisible9": 190,
    "Subcircle1_1": 37,
    "Subtitle1": 22,
    "Subtitle2": 333,
    "Subtitle20": 68,
    "Subtitle20_1": 314,
    "Subtitle6": 441,
    "Subtitle7_1": 514,
    "Subtitle8": 363,
    "TextInput1": 663,
    "TextInput1_1": 648,
    "TextInput10": 44,
    "TextInput11": 54,
    "TextInput2": 667,
    "TextInput3": 665,
    "TextInput3_1": 549,
    "TextInput3_2": 637,
    "TextInput4": 53,
    "TextInput4_1": 643,
    "TextInput5": 357,
    "TextInput6": 322,
    "TextInput7": 47,
    "TextInput9": 15,
    "TextInput9_1": 16,
    "Timer1": 79,
    "title": 285,
    "title_1": 378,
    "Title_Column1": 537,
    "Title_Column2_1": 619,
    "Title_DataCard1": 104,
    "Title_DataCard2": 446,
    "Title_DataCard4": 215,
    "Title1": 21,
    "Title1_1": 526,
    "Title1_2": 530,
    "Title10": 418,
    "Title10_1": 606,
    "Title11": 439,
    "Title11_1": 604,
    "Title13": 362,
    "Title18": 86,
    "Title2": 400,
    "Title2_1": 33,
    "Title2_2": 480,
    "Title26": 66,
    "Title26_1": 312,
    "Title3": 401,
    "Title3_1": 36,
    "Title4": 331,
    "Title5": 409,
    "Title5_2": 524,
    "Title7": 608,
    "Title8": 408,
    "Title8_1": 513,
    "Top Communities_1": 523,
    "Torch Bearers1_DataCard1": 135,
    "Torch Bearers2_DataCard1": 140,
    "Torch Bearers3_DataCard1": 145,
    "TorchImage1_DataCard1": 150,
    "TorchImage2_DataCard1": 156,
    "TorchImage3_DataCard1": 162,
    "Trend Setters1_DataCard1": 168,
    "Trend Setters2_DataCard1": 173,
    "Trend Setters3_DataCard2": 178,
    "TrendImage1_DataCard1": 183,
    "TrendImage2_DataCard1": 189,
    "TrendImage3_DataCard1": 195,
    "UpcomingGuild": 37,
    "UpcomingGuild_1": 43,
    "UserName": 62,
    "UserName_1": 308,
    "UserName_Column1": 532,
    "WeekdayGallery1_1": 31,
    "WhitePapers": 706
  },
  "ResourcesJsonIndices": {
    "Image-Anand V": 3,
    "Image-baishali roy": 4,
    "Image-facebook-square": 5,
    "Image-guild_product": 6,
    "Image-guild_supply": 7,
    "Image-guild_wealth": 8,
    "Image-Harshal Jawale": 9,
    "Image-Image": 12,
    "Image-Image (1)": 10,
    "Image-Image (2)": 11,
    "Image-Image1_2": 13,
    "Image-Image2_2": 14,
    "Image-jayakanth abhimanyu": 15,
    "Image-linkedin": 16,
    "Image-logo": 17,
    "Image-MicrosoftTeams-image (1)": 18,
    "Image-MicrosoftTeams-image (2)": 19,
    "Image-MicrosoftTeams-image (3)": 20,
    "Image-poojatest": 21,
    "Image-poojatest1": 22,
    "Image-priya": 23,
    "Image-priyatest": 24,
    "Image-priyatest1": 25,
    "Image-Quotes1": 26,
    "Image-Quotes2": 27,
    "Image-Rohan Kudav": 28,
    "Image-SampleImage": 0,
    "Image-sanjeev korupolu": 29,
    "Image-soundarya cholkar": 30,
    "Image-square-facebook": 31,
    "Image-square-twitter": 32,
    "Image-testomonial": 33,
    "Image-youtube": 34,
    "Pdf-SamplePdf": 1,
    "Video-SampleVideo": 2
  },
  "RuleScreenIdWithoutScreen": {},
  "TemplateVersions": {},
  "VolatileProperties": {
    "AnalysisLoadTime": 4.3961363,
    "ControlCount": {
      "0927d2b0e1b146c68bb9d9479edc1044": 1,
      "62dc4f1561b4448e901618e4647b41b4": 5,
      "923589e162334ba3ac42a49447cb3358": 2,
      "abc5859afff742348a300a44f7269761": 1,
      "addMedia": 10,
      "arrow": 2,
      "attachments": 6,
      "barChart": 4,
      "button": 65,
      "circle": 2,
      "dataCard": 33,
      "dataTable": 5,
      "dataTableColumn": 11,
      "datepicker": 4,
      "dropdown": 10,
      "f210c8996a1c4890ba04d40592a3d7d0": 2,
      "f519ced9060241e4947d9bc36dcc7f62": 2,
      "fluidGrid": 12,
      "form": 8,
      "gallery": 14,
      "galleryTemplate": 14,
      "group": 19,
      "groupContainer": 4,
      "htmlViewer": 2,
      "icon": 51,
      "image": 51,
      "label": 245,
      "legend": 10,
      "lineChart": 3,
      "microsoftStreamPlayback": 1,
      "pdfViewer": 1,
      "pieChart": 3,
      "rectangle": 35,
      "richTextEditor": 3,
      "screen": 22,
      "star": 1,
      "text": 37,
      "timer": 1,
      "typedDataCard": 35
    },
    "DeserializationLoadTime": 7.9137533,
    "ErrorCount": 14
  },
  "WasLocalDatabaseReferencesEmpty": false
}